{
    "bee": [
        "bee"
    ], 
    "beeeeeflmnnst": [
        "enfeeblements"
    ], 
    "beeeeeflmnnt": [
        "enfeeblement"
    ], 
    "beeeeeglmnnrttt": [
        "gentlemenbetter"
    ], 
    "beeeeekpr": [
        "beekeeper"
    ], 
    "beeeeekprs": [
        "beekeepers"
    ], 
    "beeeefln": [
        "enfeeble"
    ], 
    "beeeeflns": [
        "enfeebles"
    ], 
    "beeeeflnss": [
        "feebleness"
    ], 
    "beeeefr": [
        "freebee"
    ], 
    "beeeefrs": [
        "freebees"
    ], 
    "beeeegiknp": [
        "beekeeping"
    ], 
    "beeeegimnst": [
        "besiegement"
    ], 
    "beeeehillmorssv": [
        "overembellishes"
    ], 
    "beeeehilnprrs": [
        "reprehensible"
    ], 
    "beeeehioprrrst": [
        "robespierrethe"
    ], 
    "beeeeiilmorstt": [
        "biotelemetries"
    ], 
    "beeeeillstv": [
        "believeslet"
    ], 
    "beeeeilnrrsssv": [
        "reversibleness"
    ], 
    "beeeelmmnstzz": [
        "embezzlements"
    ], 
    "beeeelmmntzz": [
        "embezzlement"
    ], 
    "beeeemmrrr": [
        "rememberer"
    ], 
    "beeeemmrrrs": [
        "rememberers"
    ], 
    "beeefgilnn": [
        "enfeebling"
    ], 
    "beeefiillnnssx": [
        "inflexibleness"
    ], 
    "beeefir": [
        "beefier", 
        "freebie"
    ], 
    "beeefirs": [
        "freebies"
    ], 
    "beeefist": [
        "beefiest"
    ], 
    "beeefl": [
        "feeble"
    ], 
    "beeefllort": [
        "beforetell"
    ], 
    "beeeflr": [
        "feebler"
    ], 
    "beeeflss": [
        "beefless"
    ], 
    "beeeflst": [
        "feeblest"
    ], 
    "beeefnortw": [
        "beforewent"
    ], 
    "beeefoorrst": [
        "freebooters"
    ], 
    "beeefoorrt": [
        "freebooter"
    ], 
    "beeeftw": [
        "webfeet"
    ], 
    "beeegghnnprttttuwww": [
        "httpwwwgutenbergnet"
    ], 
    "beeeggiiinnnor": [
        "bioengineering"
    ], 
    "beeeggnnrttuwww": [
        "wwwgutenbergnet"
    ], 
    "beeeghiillmnorsv": [
        "overembellishing"
    ], 
    "beeeghiilmnorrsstt": [
        "terriblesomethings"
    ], 
    "beeegijllnw": [
        "bejewelling"
    ], 
    "beeegijlnw": [
        "bejeweling"
    ], 
    "beeegilllnrty": [
        "belligerently"
    ], 
    "beeegillnnnorst": [
        "nonbelligerents"
    ], 
    "beeegillnnnort": [
        "nonbelligerent"
    ], 
    "beeegillnns": [
        "enginebells"
    ], 
    "beeegillnrst": [
        "belligerents"
    ], 
    "beeegillnrt": [
        "belligerent"
    ], 
    "beeegillnss": [
        "legibleness"
    ], 
    "beeegilmnstu": [
        "beguilements"
    ], 
    "beeegilmntu": [
        "beguilement"
    ], 
    "beeegimmnrr": [
        "remembering"
    ], 
    "beeegimns": [
        "beseeming"
    ], 
    "beeegioorrss": [
        "gooseberries"
    ], 
    "beeegirs": [
        "besieger"
    ], 
    "beeegirss": [
        "besiegers"
    ], 
    "beeegis": [
        "besiege"
    ], 
    "beeegiss": [
        "besieges"
    ], 
    "beeeglmnnot": [
        "englobement"
    ], 
    "beeeglnrt": [
        "greenbelt"
    ], 
    "beeegnoow": [
        "woebegone"
    ], 
    "beeegnotw": [
        "gobetween"
    ], 
    "beeegrr": [
        "bergere"
    ], 
    "beeegrstt": [
        "begetters"
    ], 
    "beeegrtt": [
        "begetter"
    ], 
    "beeehhlmt": [
        "bethlehem"
    ], 
    "beeehillmmnsst": [
        "embellishments"
    ], 
    "beeehillmmnst": [
        "embellishment"
    ], 
    "beeehillmorsv": [
        "overembellish"
    ], 
    "beeehillmrs": [
        "embellisher"
    ], 
    "beeehillmrss": [
        "embellishers"
    ], 
    "beeehillmss": [
        "embellishes"
    ], 
    "beeehilnprrsy": [
        "reprehensibly"
    ], 
    "beeehiltv": [
        "believeth"
    ], 
    "beeehisv": [
        "beehives"
    ], 
    "beeehiv": [
        "beehive"
    ], 
    "beeehllor": [
        "hellebore"
    ], 
    "beeehllors": [
        "hellebores"
    ], 
    "beeehllpss": [
        "sheepbells"
    ], 
    "beeehllrrs": [
        "herbseller"
    ], 
    "beeehllrstw": [
        "bellwethers"
    ], 
    "beeehllrtw": [
        "bellwether"
    ], 
    "beeehlrrssstu": [
        "brusselsthere"
    ], 
    "beeehmortt": [
        "homebetter"
    ], 
    "beeehnosy": [
        "honeybees"
    ], 
    "beeehnotv": [
        "beethoven"
    ], 
    "beeehnoy": [
        "honeybee"
    ], 
    "beeehns": [
        "shebeen"
    ], 
    "beeehnss": [
        "shebeens"
    ], 
    "beeeiiiiilnprssstx": [
        "inexpressibilities"
    ], 
    "beeeiiiilprrssst": [
        "repressibilities"
    ], 
    "beeeiiklsw": [
        "biweeklies"
    ], 
    "beeeiilmnprssss": [
        "permissibleness"
    ], 
    "beeeiilnnoprrssss": [
        "irresponsibleness"
    ], 
    "beeeiilnprssx": [
        "inexpressible"
    ], 
    "beeeiilprrrss": [
        "irrepressible"
    ], 
    "beeeiilrrrsv": [
        "irreversible"
    ], 
    "beeeiinoprrt": [
        "bertinpoiree"
    ], 
    "beeeikl": [
        "beelike"
    ], 
    "beeeill": [
        "libelee"
    ], 
    "beeeilll": [
        "libellee"
    ], 
    "beeeilllloswy": [
        "yellowbellies"
    ], 
    "beeeillllv": [
        "belleville"
    ], 
    "beeeillls": [
        "libellees"
    ], 
    "beeeillmnttt": [
        "belittlement"
    ], 
    "beeeillnorsssu": [
        "rebelliousness"
    ], 
    "beeeills": [
        "libelees"
    ], 
    "beeeilmortty": [
        "biotelemetry"
    ], 
    "beeeilmptx": [
        "exemptible"
    ], 
    "beeeiln": [
        "beeline"
    ], 
    "beeeilnnoprssss": [
        "responsibleness"
    ], 
    "beeeilnnorrsv": [
        "nonreversible"
    ], 
    "beeeilnnorsv": [
        "nonbelievers"
    ], 
    "beeeilnnorv": [
        "nonbeliever"
    ], 
    "beeeilnnssss": [
        "sensibleness"
    ], 
    "beeeilnprtv": [
        "preventible"
    ], 
    "beeeilnrrsst": [
        "terribleness"
    ], 
    "beeeilnrsuv": [
        "unbelievers"
    ], 
    "beeeilnruv": [
        "unbeliever"
    ], 
    "beeeilns": [
        "beelines"
    ], 
    "beeeilnstx": [
        "extensible"
    ], 
    "beeeilorssttuv": [
        "oversubtleties"
    ], 
    "beeeilprrss": [
        "repressible"
    ], 
    "beeeilprssx": [
        "expressible"
    ], 
    "beeeilrrsv": [
        "reversible"
    ], 
    "beeeilrrtv": [
        "revertible"
    ], 
    "beeeilrsv": [
        "believers"
    ], 
    "beeeilrv": [
        "believer"
    ], 
    "beeeilsv": [
        "believes"
    ], 
    "beeeilv": [
        "believe"
    ], 
    "beeeimmnrrsstu": [
        "reimbursements"
    ], 
    "beeeimmnrrstu": [
        "reimbursement"
    ], 
    "beeeimmnrsttt": [
        "embitterments"
    ], 
    "beeeimmnrttt": [
        "embitterment"
    ], 
    "beeeinosssssv": [
        "obsessiveness"
    ], 
    "beeeinrssz": [
        "breeziness"
    ], 
    "beeeintvw": [
        "vibetween"
    ], 
    "beeeioprrrs": [
        "robespierre"
    ], 
    "beeeioprrrss": [
        "robespierres"
    ], 
    "beeeioqrtuu": [
        "bouquetiere"
    ], 
    "beeeirr": [
        "beerier"
    ], 
    "beeeirrsstw": [
        "sweetbriers"
    ], 
    "beeeirrstw": [
        "sweetbrier"
    ], 
    "beeeirrsw": [
        "breweries"
    ], 
    "beeeirrz": [
        "breezier"
    ], 
    "beeeirsstttw": [
        "bittersweets"
    ], 
    "beeeirst": [
        "beeriest"
    ], 
    "beeeirstttw": [
        "bittersweet"
    ], 
    "beeeirstz": [
        "breeziest"
    ], 
    "beeejlsw": [
        "bejewels"
    ], 
    "beeejlsz": [
        "jezebels"
    ], 
    "beeejlw": [
        "bejewel"
    ], 
    "beeejlz": [
        "jezebel"
    ], 
    "beeekkoopr": [
        "bookkeeper"
    ], 
    "beeekkooprs": [
        "bookkeepers"
    ], 
    "beeeklry": [
        "berkeley"
    ], 
    "beeellnnotvy": [
        "benevolently"
    ], 
    "beeellrsst": [
        "bestseller"
    ], 
    "beeellrsv": [
        "bevellers"
    ], 
    "beeellrv": [
        "beveller"
    ], 
    "beeelluv": [
        "bellevue"
    ], 
    "beeelmmnst": [
        "emblements"
    ], 
    "beeelmnnnost": [
        "ennoblements"
    ], 
    "beeelmnnnot": [
        "ennoblement"
    ], 
    "beeelmns": [
        "ensemble"
    ], 
    "beeelmnss": [
        "ensembles"
    ], 
    "beeelmpry": [
        "pemberley"
    ], 
    "beeelmrs": [
        "resemble"
    ], 
    "beeelmrss": [
        "resembles"
    ], 
    "beeelmrsst": [
        "resemblest"
    ], 
    "beeelmrszz": [
        "embezzlers"
    ], 
    "beeelmrzz": [
        "embezzler"
    ], 
    "beeelmszz": [
        "embezzles"
    ], 
    "beeelmzz": [
        "embezzle"
    ], 
    "beeelnnotv": [
        "benevolent"
    ], 
    "beeelnoossst": [
        "obsoleteness"
    ], 
    "beeelnoptuw": [
        "loupbetween"
    ], 
    "beeelort": [
        "treebole"
    ], 
    "beeelprsss": [
        "preblesses"
    ], 
    "beeelpttw": [
        "beweptlet"
    ], 
    "beeelrstw": [
        "beltsewer"
    ], 
    "beeelrsv": [
        "bevelers"
    ], 
    "beeelrv": [
        "beveler"
    ], 
    "beeelsssu": [
        "sublessee"
    ], 
    "beeelst": [
        "beetles"
    ], 
    "beeelt": [
        "beetle"
    ], 
    "beeelv": [
        "bleeve"
    ], 
    "beeemmrr": [
        "remember"
    ], 
    "beeemmrrs": [
        "remembers"
    ], 
    "beeemnrttt": [
        "betterment"
    ], 
    "beeemprst": [
        "september"
    ], 
    "beeemrss": [
        "bessemer"
    ], 
    "beeems": [
        "beseem"
    ], 
    "beeemss": [
        "beseems"
    ], 
    "beeennsz": [
        "benzenes"
    ], 
    "beeennz": [
        "benzene"
    ], 
    "beeenooprrsssstu": [
        "obstreperousness"
    ], 
    "beeenopprsty": [
        "teenyboppers"
    ], 
    "beeenopprty": [
        "teenybopper"
    ], 
    "beeenorsssv": [
        "verboseness"
    ], 
    "beeenorstt": [
        "bonesetter"
    ], 
    "beeenstw": [
        "betweens"
    ], 
    "beeentw": [
        "between"
    ], 
    "beeepr": [
        "beeper"
    ], 
    "beeeprs": [
        "beepers"
    ], 
    "beeersstt": [
        "besetters"
    ], 
    "beeerstt": [
        "besetter"
    ], 
    "beeersz": [
        "breezes"
    ], 
    "beeerz": [
        "breeze"
    ], 
    "beeesv": [
        "beeves"
    ], 
    "beef": [
        "beef"
    ], 
    "beeffgirsu": [
        "febrifuges"
    ], 
    "beeffgiru": [
        "febrifuge"
    ], 
    "beeffinoorsu": [
        "buffooneries"
    ], 
    "beeffiorsu": [
        "sebouriffe"
    ], 
    "beeffot": [
        "boffete"
    ], 
    "beeffrstu": [
        "buffeters"
    ], 
    "beeffrtu": [
        "buffeter"
    ], 
    "beefgiinnt": [
        "benefiting"
    ], 
    "beefgiinntt": [
        "benefitting"
    ], 
    "beefgin": [
        "beefing"
    ], 
    "beefginrrsttu": [
        "butterfingers"
    ], 
    "beefginrsuz": [
        "subfreezing"
    ], 
    "beefgrsstuu": [
        "subterfuges"
    ], 
    "beefgrstuu": [
        "subterfuge"
    ], 
    "beefhils": [
        "feeblish"
    ], 
    "beefhilssu": [
        "bluefishes"
    ], 
    "beefhimnrrstu": [
        "refurbishment"
    ], 
    "beefhinoss": [
        "bonefishes"
    ], 
    "beefhirrssu": [
        "refurbishes"
    ], 
    "beefhirssttu": [
        "butterfishes"
    ], 
    "beefiiknow": [
        "bowieknife"
    ], 
    "beefiillnx": [
        "inflexible"
    ], 
    "beefiilms": [
        "misbelief"
    ], 
    "beefiilmss": [
        "misbeliefs"
    ], 
    "beefiilnrr": [
        "inferrible"
    ], 
    "beefiilrrsstu": [
        "filibusterers"
    ], 
    "beefiilrrstu": [
        "filibusterer"
    ], 
    "beefiirsv": [
        "verbifies"
    ], 
    "beefiirsz": [
        "fiberizes"
    ], 
    "beefiirz": [
        "fiberize"
    ], 
    "beefil": [
        "belief"
    ], 
    "beefillnnox": [
        "nonflexible"
    ], 
    "beefillx": [
        "flexible"
    ], 
    "beefilnsssu": [
        "fusibleness"
    ], 
    "beefilnsu": [
        "unbeliefs"
    ], 
    "beefilnu": [
        "unbelief"
    ], 
    "beefiloru": [
        "befoulier"
    ], 
    "beefilr": [
        "febrile"
    ], 
    "beefilrs": [
        "belfries"
    ], 
    "beefilrss": [
        "briefless"
    ], 
    "beefilrsttu": [
        "butterflies"
    ], 
    "beefils": [
        "beliefs"
    ], 
    "beefilty": [
        "itfeebly"
    ], 
    "beefily": [
        "beefily"
    ], 
    "beefinrss": [
        "briefness"
    ], 
    "beefinst": [
        "benefits"
    ], 
    "beefint": [
        "benefit"
    ], 
    "beefiorsx": [
        "fireboxes"
    ], 
    "beefiort": [
        "beforeit"
    ], 
    "beefirr": [
        "briefer"
    ], 
    "beefirs": [
        "frisbee"
    ], 
    "beefirss": [
        "frisbees"
    ], 
    "beefirst": [
        "briefest"
    ], 
    "beefistux": [
        "tubifexes"
    ], 
    "beefll": [
        "befell"
    ], 
    "beeflu": [
        "lebeuf"
    ], 
    "beefly": [
        "feebly"
    ], 
    "beefnorr": [
        "freeborn"
    ], 
    "beefoorst": [
        "freeboots"
    ], 
    "beefoort": [
        "freeboot"
    ], 
    "beefor": [
        "before"
    ], 
    "beefory": [
        "forebye"
    ], 
    "beefrt": [
        "bereft"
    ], 
    "beefs": [
        "beefs"
    ], 
    "beefy": [
        "beefy"
    ], 
    "beeggghnoprrtttuwww": [
        "httpwwwgutenbergorg"
    ], 
    "beegggnorrtuwww": [
        "wwwgutenbergorg"
    ], 
    "beeggiilln": [
        "negligible"
    ], 
    "beeggiimnstt": [
        "misbegetting"
    ], 
    "beeggiins": [
        "besieging"
    ], 
    "beeggilsstu": [
        "suggestible"
    ], 
    "beeggintt": [
        "begetting"
    ], 
    "beeggirsu": [
        "buggeries"
    ], 
    "beeggloorst": [
        "bootleggers"
    ], 
    "beeggloort": [
        "bootlegger"
    ], 
    "beeggmnrsttu": [
        "gutenbergtms"
    ], 
    "beeggmnrttu": [
        "gutenbergtm"
    ], 
    "beeggnrstu": [
        "gutenbergs"
    ], 
    "beeggnrtu": [
        "gutenberg"
    ], 
    "beeghiiinrtx": [
        "reexhibiting"
    ], 
    "beeghiillmns": [
        "embellishing"
    ], 
    "beeghiilln": [
        "ghibelline"
    ], 
    "beeghiillns": [
        "ghibellines"
    ], 
    "beeghiilnnorss": [
        "neighborliness"
    ], 
    "beeghinnorr": [
        "herringbone"
    ], 
    "beeghinnorrs": [
        "herringbones"
    ], 
    "beeghinrrst": [
        "brighteners"
    ], 
    "beeghinrrt": [
        "brightener"
    ], 
    "beeghnoorrt": [
        "brothergone"
    ], 
    "beegi": [
        "beige"
    ], 
    "beegiiiillst": [
        "legibilities"
    ], 
    "beegiiilllnntu": [
        "unintelligible"
    ], 
    "beegiiilllnt": [
        "intelligible"
    ], 
    "beegiiilln": [
        "ineligible"
    ], 
    "beegiiillns": [
        "ineligibles"
    ], 
    "beegiiinnst": [
        "benignities"
    ], 
    "beegiill": [
        "eligible"
    ], 
    "beegiilll": [
        "illegible"
    ], 
    "beegiillnno": [
        "noneligible"
    ], 
    "beegiills": [
        "eligibles"
    ], 
    "beegiilnnuv": [
        "unbelieving"
    ], 
    "beegiilnooosx": [
        "xenobiologies"
    ], 
    "beegiilnst": [
        "ingestible"
    ], 
    "beegiilnv": [
        "believing"
    ], 
    "beegiilx": [
        "exigible"
    ], 
    "beegiimnrtt": [
        "embittering"
    ], 
    "beegiinos": [
        "biogenies"
    ], 
    "beegiioorsu": [
        "bourgeoisie"
    ], 
    "beegikknoop": [
        "bookkeeping"
    ], 
    "beegiknnot": [
        "betokening"
    ], 
    "beegill": [
        "legible"
    ], 
    "beegilllmnostt": [
        "smellingbottle"
    ], 
    "beegillnr": [
        "rebelling"
    ], 
    "beegillnrr": [
        "bellringer"
    ], 
    "beegillnsst": [
        "bestselling"
    ], 
    "beegillnv": [
        "bevelling"
    ], 
    "beegillnw": [
        "wellbeing"
    ], 
    "beegilmmn": [
        "embleming"
    ], 
    "beegilmnoorv": [
        "everblooming"
    ], 
    "beegilmnot": [
        "obligement"
    ], 
    "beegilmnow": [
        "emboweling"
    ], 
    "beegilmnrs": [
        "resembling"
    ], 
    "beegilmnzz": [
        "embezzling"
    ], 
    "beegilmoorsy": [
        "embryologies"
    ], 
    "beegilnp": [
        "bleeping"
    ], 
    "beegilnprss": [
        "preblessing"
    ], 
    "beegilnt": [
        "beetling"
    ], 
    "beegilnv": [
        "beveling"
    ], 
    "beegilo": [
        "obligee"
    ], 
    "beegilott": [
        "gibelotte"
    ], 
    "beegilrsu": [
        "beguilers"
    ], 
    "beegilru": [
        "beguiler"
    ], 
    "beegilsu": [
        "beguiles"
    ], 
    "beegilu": [
        "beguile"
    ], 
    "beegimnnrru": [
        "renumbering"
    ], 
    "beegimnorw": [
        "embowering"
    ], 
    "beegimnostt": [
        "misbegotten"
    ], 
    "beegimr": [
        "begrime"
    ], 
    "beegimrs": [
        "begrimes"
    ], 
    "beegimst": [
        "misbeget"
    ], 
    "beeginn": [
        "benigne"
    ], 
    "beeginnr": [
        "beginner"
    ], 
    "beeginnrs": [
        "beginners"
    ], 
    "beeginp": [
        "beeping"
    ], 
    "beeginrstw": [
        "bestrewing"
    ], 
    "beeginrtt": [
        "bettering"
    ], 
    "beeginrttv": [
        "brevetting"
    ], 
    "beeginrtv": [
        "breveting"
    ], 
    "beeginrz": [
        "breezing"
    ], 
    "beeginsss": [
        "bignesses"
    ], 
    "beeginssw": [
        "beeswings"
    ], 
    "beeginstt": [
        "besetting"
    ], 
    "beeginsu": [
        "beguines"
    ], 
    "beeginu": [
        "beguine"
    ], 
    "beegioorsu": [
        "bourgeoise"
    ], 
    "beegiprrssttu": [
        "petersburgits"
    ], 
    "beegirruu": [
        "bruguiere"
    ], 
    "beegis": [
        "beiges"
    ], 
    "beegisy": [
        "bigeyes"
    ], 
    "beegiy": [
        "bigeye"
    ], 
    "beegjrsu": [
        "beerjugs"
    ], 
    "beegl": [
        "glebe"
    ], 
    "beeglmmptuy": [
        "mumbletypeg"
    ], 
    "beeglno": [
        "englobe"
    ], 
    "beeglnoos": [
        "bolognese"
    ], 
    "beeglnor": [
        "grenoble"
    ], 
    "beegloorrsttt": [
        "globetrotters"
    ], 
    "beegloorrttt": [
        "globetrotter"
    ], 
    "beegmnoy": [
        "bogeymen"
    ], 
    "beegmnssstu": [
        "subsegments"
    ], 
    "beegmnsstu": [
        "subsegment"
    ], 
    "beegmrssu": [
        "submerges"
    ], 
    "beegmrsu": [
        "submerge"
    ], 
    "beegno": [
        "begone"
    ], 
    "beegnoow": [
        "wobegone"
    ], 
    "beegnott": [
        "begotten"
    ], 
    "beegnsssuu": [
        "subgenuses"
    ], 
    "beegoorrsy": [
        "gooseberry"
    ], 
    "beegopsx": [
        "pegboxes"
    ], 
    "beegprrstu": [
        "petersburg"
    ], 
    "beegr": [
        "gerbe", 
        "grebe"
    ], 
    "beegrs": [
        "grebes"
    ], 
    "beegrsssu": [
        "burgesses"
    ], 
    "beegrsu": [
        "burgees"
    ], 
    "beegru": [
        "burgee"
    ], 
    "beegst": [
        "begets"
    ], 
    "beegsuy": [
        "bugeyes"
    ], 
    "beegt": [
        "beget"
    ], 
    "beeguy": [
        "bugeye"
    ], 
    "beehhmost": [
        "behemoths"
    ], 
    "beehhmot": [
        "behemoth"
    ], 
    "beehhorrtt": [
        "brotherthe"
    ], 
    "beehiiinortx": [
        "exhibitioner"
    ], 
    "beehiilrrst": [
        "terriblehis"
    ], 
    "beehiirstx": [
        "reexhibits", 
        "exhibiters"
    ], 
    "beehiirtx": [
        "exhibiter", 
        "reexhibit"
    ], 
    "beehillms": [
        "embellish"
    ], 
    "beehilmn": [
        "blenheim"
    ], 
    "beehilmoopst": [
        "phlebotomies"
    ], 
    "beehilmost": [
        "blithesome"
    ], 
    "beehilmss": [
        "blemishes"
    ], 
    "beehilnorrss": [
        "horribleness"
    ], 
    "beehilnorrsst": [
        "brotherliness"
    ], 
    "beehilnsst": [
        "blitheness"
    ], 
    "beehilprssu": [
        "republishes"
    ], 
    "beehimmnnoprs": [
        "nonmembership"
    ], 
    "beehimmnrstu": [
        "reimbushment"
    ], 
    "beehimmprs": [
        "membership"
    ], 
    "beehimmprss": [
        "memberships"
    ], 
    "beehimnoort": [
        "theobromine"
    ], 
    "beehimoooprtt": [
        "biophotometer"
    ], 
    "beehin": [
        "behine"
    ], 
    "beehinosssty": [
        "biosyntheses"
    ], 
    "beehinssssu": [
        "businessshe"
    ], 
    "beehioprs": [
        "biosphere"
    ], 
    "beehioprss": [
        "biospheres"
    ], 
    "beehiorrsv": [
        "herbivores"
    ], 
    "beehiorrv": [
        "herbivore"
    ], 
    "beehirr": [
        "herbier"
    ], 
    "beehirrst": [
        "berthiers"
    ], 
    "beehirrt": [
        "berthier"
    ], 
    "beehirstt": [
        "hebertist"
    ], 
    "beehkloossv": [
        "bookshelves"
    ], 
    "beehknoorsu": [
        "housebroken"
    ], 
    "beehlllostu": [
        "bulletholes"
    ], 
    "beehllnt": [
        "hellbent"
    ], 
    "beehllosx": [
        "hellboxes"
    ], 
    "beehllotv": [
        "levelboth"
    ], 
    "beehlmnssu": [
        "humbleness"
    ], 
    "beehlooorrssttu": [
        "troubleshooters"
    ], 
    "beehlooorrsttu": [
        "troubleshooter"
    ], 
    "beehloot": [
        "bootheel"
    ], 
    "beehloprsy": [
        "hyperboles"
    ], 
    "beehlopry": [
        "hyperbole"
    ], 
    "beehlrss": [
        "herbless"
    ], 
    "beehlrssu": [
        "bushelers"
    ], 
    "beehlrst": [
        "blethers"
    ], 
    "beehlrsu": [
        "busheler"
    ], 
    "beehlrt": [
        "blether"
    ], 
    "beehlst": [
        "bethels"
    ], 
    "beehlt": [
        "bethel"
    ], 
    "beehmnorttt": [
        "betrothment"
    ], 
    "beehmoorst": [
        "bothersome"
    ], 
    "beehmrsy": [
        "berhymes"
    ], 
    "beehnoopsx": [
        "xenophobes"
    ], 
    "beehnoopx": [
        "xenophobe"
    ], 
    "beehnrrt": [
        "brethren"
    ], 
    "beehnrvz": [
        "brezhnev"
    ], 
    "beehntu": [
        "bethune"
    ], 
    "beehoosv": [
        "behooves"
    ], 
    "beehoov": [
        "behoove"
    ], 
    "beehop": [
        "phoebe"
    ], 
    "beehoprrsstt": [
        "stepbrothers"
    ], 
    "beehoprrstt": [
        "stepbrother"
    ], 
    "beehops": [
        "phoebes"
    ], 
    "beehorrrtvy": [
        "brothervery"
    ], 
    "beehorsssu": [
        "rosebushes"
    ], 
    "beehorsty": [
        "robesthey"
    ], 
    "beehortw": [
        "bothwere"
    ], 
    "beehosv": [
        "behoves"
    ], 
    "beehov": [
        "behove"
    ], 
    "beehrrsst": [
        "sherberts"
    ], 
    "beehrrst": [
        "sherbert"
    ], 
    "beehrrt": [
        "herbert"
    ], 
    "beehrsst": [
        "sherbets"
    ], 
    "beehrssw": [
        "beshrews"
    ], 
    "beehrst": [
        "sherbet"
    ], 
    "beehrsw": [
        "hebrews", 
        "beshrew"
    ], 
    "beehrt": [
        "hebert"
    ], 
    "beehrty": [
        "thereby"
    ], 
    "beehrw": [
        "hebrew"
    ], 
    "beehrwy": [
        "whereby"
    ], 
    "beehry": [
        "hereby"
    ], 
    "beehsst": [
        "behests"
    ], 
    "beehst": [
        "behest", 
        "thebes"
    ], 
    "beeiiiiilnoprrssst": [
        "irresponsibilities"
    ], 
    "beeiiiilnoprssst": [
        "responsibilities"
    ], 
    "beeiiiilnossstt": [
        "ostensibilities"
    ], 
    "beeiiiilnprsstxy": [
        "inexpressibility"
    ], 
    "beeiiiilnssst": [
        "sensibilities"
    ], 
    "beeiiiilrrrstvy": [
        "irreversibility"
    ], 
    "beeiiilmmprss": [
        "impermissible"
    ], 
    "beeiiilnnsssv": [
        "invisibleness"
    ], 
    "beeiiilprrssty": [
        "repressibility"
    ], 
    "beeiiilrrsst": [
        "irresistible"
    ], 
    "beeiiilrrstvy": [
        "reversibility"
    ], 
    "beeiiklnsssu": [
        "businesslike"
    ], 
    "beeiilmnopssss": [
        "impossibleness"
    ], 
    "beeiilmnprssu": [
        "unimpressible"
    ], 
    "beeiilmnrst": [
        "timberlines"
    ], 
    "beeiilmnrt": [
        "timberline"
    ], 
    "beeiilmprss": [
        "impressible", 
        "permissible"
    ], 
    "beeiilnnss": [
        "insensible"
    ], 
    "beeiilnoorrstu": [
        "benoitsurloire"
    ], 
    "beeiilnoprrss": [
        "irresponsible"
    ], 
    "beeiilnosstu": [
        "nebulosities"
    ], 
    "beeiilnpprsssu": [
        "insuppressible"
    ], 
    "beeiilnprssxy": [
        "inexpressibly"
    ], 
    "beeiilnrst": [
        "libertines"
    ], 
    "beeiilnrt": [
        "libertine"
    ], 
    "beeiilnrtv": [
        "invertible"
    ], 
    "beeiilnstv": [
        "investible"
    ], 
    "beeiilprrrssy": [
        "irrepressibly"
    ], 
    "beeiilrrrsvy": [
        "irreversibly"
    ], 
    "beeiilrsst": [
        "resistible"
    ], 
    "beeiilrst": [
        "liberties", 
        "libertise"
    ], 
    "beeiimnnnosssssuv": [
        "nonsubmissiveness"
    ], 
    "beeiimnoprssst": [
        "bestpermission"
    ], 
    "beeiimnsssssuv": [
        "submissiveness"
    ], 
    "beeiimoorsst": [
        "tombeissoire"
    ], 
    "beeiimorst": [
        "biometries"
    ], 
    "beeiinrty": [
        "inebriety"
    ], 
    "beeiiorsst": [
        "sobrieties"
    ], 
    "beeiiosst": [
        "obesities"
    ], 
    "beeiirrttuv": [
        "retributive"
    ], 
    "beeiirstv": [
        "brevities"
    ], 
    "beeijlrrsttu": [
        "terriblejust"
    ], 
    "beeijlsu": [
        "jubilees"
    ], 
    "beeijlu": [
        "jubilee"
    ], 
    "beeikl": [
        "belike"
    ], 
    "beeiklmru": [
        "berkelium"
    ], 
    "beeiklnprs": [
        "besprinkle"
    ], 
    "beeiklnprss": [
        "besprinkles"
    ], 
    "beeiklorw": [
        "bowerlike"
    ], 
    "beeiklrry": [
        "berrylike"
    ], 
    "beeiklwy": [
        "biweekly"
    ], 
    "beeil": [
        "belie"
    ], 
    "beeilllmmov": [
        "villemomble"
    ], 
    "beeilllntuy": [
        "ebulliently"
    ], 
    "beeilllorsuy": [
        "rebelliously"
    ], 
    "beeilllr": [
        "libeller"
    ], 
    "beeilllrs": [
        "libellers"
    ], 
    "beeillmpru": [
        "lumberpile"
    ], 
    "beeillmsu": [
        "emulsible"
    ], 
    "beeillnor": [
        "rebellion"
    ], 
    "beeillnors": [
        "rebellions"
    ], 
    "beeillnsssu": [
        "bullinesses"
    ], 
    "beeillnst": [
        "beltlines"
    ], 
    "beeillnt": [
        "beltline"
    ], 
    "beeillntu": [
        "ebullient"
    ], 
    "beeilloors": [
        "rolleboise"
    ], 
    "beeilloprty": [
        "libertypole"
    ], 
    "beeillopst": [
        "potbellies"
    ], 
    "beeillorsu": [
        "rebellious"
    ], 
    "beeillossw": [
        "sowbellies"
    ], 
    "beeillqsu": [
        "bequilles"
    ], 
    "beeillr": [
        "libeler"
    ], 
    "beeillrs": [
        "libelers"
    ], 
    "beeillrsstt": [
        "belletrists"
    ], 
    "beeillrst": [
        "billeters"
    ], 
    "beeillrstt": [
        "belletrist", 
        "belittlers"
    ], 
    "beeillrt": [
        "billeter"
    ], 
    "beeillrtt": [
        "betterill", 
        "belittler"
    ], 
    "beeillrw": [
        "bellwire"
    ], 
    "beeills": [
        "bellies"
    ], 
    "beeillstt": [
        "billettes", 
        "belittles"
    ], 
    "beeilltt": [
        "belittle"
    ], 
    "beeilmmnorst": [
        "embroilments"
    ], 
    "beeilmmnort": [
        "embroilment"
    ], 
    "beeilmnnss": [
        "nimbleness"
    ], 
    "beeilmnrss": [
        "limberness"
    ], 
    "beeilmnsssu": [
        "sublimeness"
    ], 
    "beeilmprsu": [
        "plumberies"
    ], 
    "beeilmrr": [
        "limberer"
    ], 
    "beeilmrrsu": [
        "mulberries"
    ], 
    "beeilmrrt": [
        "tremblier"
    ], 
    "beeilmrst": [
        "limberest"
    ], 
    "beeilmrstt": [
        "trembliest"
    ], 
    "beeilms": [
        "beslime", 
        "besmile"
    ], 
    "beeilnns": [
        "blennies"
    ], 
    "beeilnnssu": [
        "unsensible"
    ], 
    "beeilnoprss": [
        "responsible"
    ], 
    "beeilnoqssu": [
        "obliqueness"
    ], 
    "beeilnosst": [
        "ostensible"
    ], 
    "beeilnpprsssuu": [
        "unsuppressible"
    ], 
    "beeilnrrs": [
        "berliners"
    ], 
    "beeilnrss": [
        "sensibler"
    ], 
    "beeilnrsstt": [
        "brittleness"
    ], 
    "beeilnrssttu": [
        "listenersbut"
    ], 
    "beeilnrsstuvy": [
        "subserviently"
    ], 
    "beeilnrsuz": [
        "nebulizers"
    ], 
    "beeilnruz": [
        "nebulizer"
    ], 
    "beeilnry": [
        "beryline"
    ], 
    "beeilnss": [
        "sensible", 
        "belissen"
    ], 
    "beeilnsss": [
        "sensibles"
    ], 
    "beeilnssst": [
        "sensiblest"
    ], 
    "beeilnst": [
        "tensible"
    ], 
    "beeilnsu": [
        "nebulise"
    ], 
    "beeilnsuz": [
        "nebulizes"
    ], 
    "beeilnuz": [
        "nebulize"
    ], 
    "beeilopssss": [
        "possessible"
    ], 
    "beeilors": [
        "erosible"
    ], 
    "beeilosssvy": [
        "obsessively"
    ], 
    "beeilosttu": [
        "oubliettes"
    ], 
    "beeilottu": [
        "oubliette"
    ], 
    "beeilpprsssu": [
        "suppressible"
    ], 
    "beeilr": [
        "belier"
    ], 
    "beeilrrst": [
        "terribles"
    ], 
    "beeilrrsvy": [
        "reversibly"
    ], 
    "beeilrrt": [
        "terrible"
    ], 
    "beeilrs": [
        "beliers"
    ], 
    "beeilrssuvvy": [
        "subversively"
    ], 
    "beeilrstu": [
        "butleries"
    ], 
    "beeilrv": [
        "verbile"
    ], 
    "beeilryz": [
        "breezily"
    ], 
    "beeils": [
        "belies"
    ], 
    "beeilssttu": [
        "subtleties"
    ], 
    "beeilsstuv": [
        "vestibules"
    ], 
    "beeilstuv": [
        "vestibule"
    ], 
    "beeilv": [
        "blieve"
    ], 
    "beeimnnosssuw": [
        "businesswomen"
    ], 
    "beeimnnsssu": [
        "businessmen"
    ], 
    "beeimnorstw": [
        "tribeswomen"
    ], 
    "beeimnrst": [
        "tribesmen"
    ], 
    "beeimort": [
        "biometer"
    ], 
    "beeimprsstt": [
        "septembrist"
    ], 
    "beeimr": [
        "bireme", 
        "bemire"
    ], 
    "beeimrrssu": [
        "reimburses"
    ], 
    "beeimrrsu": [
        "reimburse"
    ], 
    "beeimrs": [
        "bemires", 
        "biremes"
    ], 
    "beeimrsst": [
        "bimesters"
    ], 
    "beeimrst": [
        "bimester"
    ], 
    "beeimrstt": [
        "embitters"
    ], 
    "beeimrtt": [
        "betterim", 
        "embitter"
    ], 
    "beeimst": [
        "betimes"
    ], 
    "beeimt": [
        "betime"
    ], 
    "beeinnoorstu": [
        "boutonnieres"
    ], 
    "beeinnoortu": [
        "boutonniere"
    ], 
    "beeinnorssstuuv": [
        "unobtrusiveness"
    ], 
    "beeinnott": [
        "bentonite"
    ], 
    "beeinnotuv": [
        "eveninbout"
    ], 
    "beeinnr": [
        "brienne"
    ], 
    "beeinns": [
        "bennies"
    ], 
    "beeinnsuv": [
        "bienvenus"
    ], 
    "beeinnsz": [
        "benzines"
    ], 
    "beeinnuv": [
        "bienvenu"
    ], 
    "beeinnz": [
        "benzine"
    ], 
    "beeinooqssssuu": [
        "obsequiousness"
    ], 
    "beeinoorsssstu": [
        "boisterousness"
    ], 
    "beeinorssstuv": [
        "obtrusiveness"
    ], 
    "beeinos": [
        "ebonies"
    ], 
    "beeinost": [
        "ebonites", 
        "betonies"
    ], 
    "beeinot": [
        "ebonite"
    ], 
    "beeinprtu": [
        "repinebut"
    ], 
    "beeinrrs": [
        "berniers"
    ], 
    "beeinrsstt": [
        "bitterness"
    ], 
    "beeinrsstu": [
        "subentries"
    ], 
    "beeinrsstuv": [
        "subservient"
    ], 
    "beeinrstt": [
        "isbettern"
    ], 
    "beeinrz": [
        "zebrine"
    ], 
    "beeinssssu": [
        "businesses"
    ], 
    "beeinssssuy": [
        "businessyes"
    ], 
    "beeioorst": [
        "booteries"
    ], 
    "beeioqssu": [
        "obsequies"
    ], 
    "beeiorstv": [
        "overbites"
    ], 
    "beeiorsw": [
        "boweries"
    ], 
    "beeiorsz": [
        "soberize"
    ], 
    "beeiortv": [
        "overbite"
    ], 
    "beeiosssv": [
        "obsessive"
    ], 
    "beeiprstu": [
        "puberties"
    ], 
    "beeiqrsttu": [
        "briquettes"
    ], 
    "beeiqrttu": [
        "briquette"
    ], 
    "beeiquz": [
        "bezique"
    ], 
    "beeirrs": [
        "berries"
    ], 
    "beeirrsu": [
        "reburies"
    ], 
    "beeirrtt": [
        "bitterer"
    ], 
    "beeirrttu": [
        "retribute", 
        "butterier"
    ], 
    "beeirrv": [
        "brevier"
    ], 
    "beeirsssu": [
        "subseries"
    ], 
    "beeirsssuvv": [
        "subversives"
    ], 
    "beeirssuvv": [
        "subversive"
    ], 
    "beeirsttt": [
        "bitterest"
    ], 
    "beeirstttu": [
        "butteriest"
    ], 
    "beeirsttu": [
        "butteries"
    ], 
    "beeirstu": [
        "uberties"
    ], 
    "beeirv": [
        "bievre"
    ], 
    "beeiss": [
        "bessie"
    ], 
    "beeisv": [
        "bevies"
    ], 
    "beeisx": [
        "ibexes"
    ], 
    "beejkosux": [
        "jukeboxes"
    ], 
    "beejlnossss": [
        "joblessness"
    ], 
    "beeklloors": [
        "bookseller"
    ], 
    "beeklloorss": [
        "booksellers"
    ], 
    "beeklr": [
        "kleber"
    ], 
    "beekmos": [
        "besmoke"
    ], 
    "beeknnorss": [
        "brokenness"
    ], 
    "beeknops": [
        "bespoken"
    ], 
    "beeknost": [
        "betokens"
    ], 
    "beeknot": [
        "betoken"
    ], 
    "beekops": [
        "bespoke"
    ], 
    "beekopy": [
        "boykeep"
    ], 
    "beekrrs": [
        "berserk"
    ], 
    "beekrrss": [
        "berserks"
    ], 
    "beekrrsu": [
        "rebukers"
    ], 
    "beekrru": [
        "rebuker"
    ], 
    "beekrsu": [
        "rebukes"
    ], 
    "beekru": [
        "rebuke"
    ], 
    "beell": [
        "belle", 
        "lebel"
    ], 
    "beellllowyy": [
        "yellowbelly"
    ], 
    "beellmn": [
        "bellmen"
    ], 
    "beellmnoot": [
        "montebello"
    ], 
    "beellmoorstuy": [
        "troublesomely"
    ], 
    "beelloosty": [
        "obsoletely"
    ], 
    "beellorsw": [
        "bellowers"
    ], 
    "beellort": [
        "tolerble"
    ], 
    "beellortw": [
        "belltower"
    ], 
    "beellorw": [
        "bellower"
    ], 
    "beellru": [
        "berulle"
    ], 
    "beellrux": [
        "bruxelle"
    ], 
    "beells": [
        "belles"
    ], 
    "beellsst": [
        "beltless"
    ], 
    "beellssuv": [
        "sublevels"
    ], 
    "beellsuv": [
        "sublevel"
    ], 
    "beelmm": [
        "emblem"
    ], 
    "beelmmnru": [
        "lumbermen"
    ], 
    "beelmms": [
        "emblems"
    ], 
    "beelmnno": [
        "noblemen"
    ], 
    "beelmnnoow": [
        "noblewomen"
    ], 
    "beelmnoru": [
        "melbourne"
    ], 
    "beelmnrssu": [
        "numberless"
    ], 
    "beelmnsu": [
        "bluesmen"
    ], 
    "beelmoorssttu": [
        "troublesomest"
    ], 
    "beelmoorstu": [
        "troublesome"
    ], 
    "beelmrrssu": [
        "slumberers"
    ], 
    "beelmrrst": [
        "tremblers"
    ], 
    "beelmrrsu": [
        "slumberer", 
        "lumberers"
    ], 
    "beelmrrt": [
        "trembler"
    ], 
    "beelmrru": [
        "lumberer"
    ], 
    "beelmrst": [
        "trembles"
    ], 
    "beelmrt": [
        "tremble"
    ], 
    "beelmru": [
        "blemeur"
    ], 
    "beelnno": [
        "ennoble"
    ], 
    "beelnnor": [
        "ennobler"
    ], 
    "beelnnors": [
        "ennoblers"
    ], 
    "beelnnos": [
        "ennobles"
    ], 
    "beelnnoss": [
        "nobleness"
    ], 
    "beelnoss": [
        "boneless", 
        "noblesse"
    ], 
    "beelnosss": [
        "noblesses"
    ], 
    "beelnossu": [
        "bluenoses"
    ], 
    "beelnosu": [
        "bluenose"
    ], 
    "beelnot": [
        "bonelet"
    ], 
    "beelnqsstuuy": [
        "subsequently"
    ], 
    "beelnssstu": [
        "subtleness"
    ], 
    "beelnssu": [
        "blueness"
    ], 
    "beelnsttu": [
        "betelnuts"
    ], 
    "beelnttu": [
        "betelnut"
    ], 
    "beelnu": [
        "nebule"
    ], 
    "beelooprrsstuy": [
        "obstreperously"
    ], 
    "beeloosst": [
        "obsoletes"
    ], 
    "beeloost": [
        "obsolete"
    ], 
    "beelorrsst": [
        "bolsterers"
    ], 
    "beelorrst": [
        "bolsterer"
    ], 
    "beelorsttuvy": [
        "oversubtlety"
    ], 
    "beelorstuv": [
        "oversubtle"
    ], 
    "beelorsvy": [
        "verbosely"
    ], 
    "beelorttx": [
        "letterbox"
    ], 
    "beelosty": [
        "eyebolts"
    ], 
    "beelosy": [
        "obesely"
    ], 
    "beeloty": [
        "eyebolt"
    ], 
    "beelp": [
        "bleep", 
        "plebe"
    ], 
    "beelprss": [
        "prebless"
    ], 
    "beelps": [
        "bleeps", 
        "plebes"
    ], 
    "beelpstu": [
        "sleepbut"
    ], 
    "beelqrssuu": [
        "burlesques"
    ], 
    "beelqrsuu": [
        "burlesque"
    ], 
    "beelr": [
        "rebel"
    ], 
    "beelrrsstu": [
        "blusterers"
    ], 
    "beelrrstu": [
        "blusterer"
    ], 
    "beelrs": [
        "rebels"
    ], 
    "beelrss": [
        "rebless", 
        "blesser"
    ], 
    "beelrsss": [
        "blessers"
    ], 
    "beelrssv": [
        "verbless"
    ], 
    "beelrst": [
        "trebles"
    ], 
    "beelrstuu": [
        "trueblues"
    ], 
    "beelrt": [
        "treble"
    ], 
    "beelrtuu": [
        "trueblue"
    ], 
    "beelsss": [
        "blesses"
    ], 
    "beelsstu": [
        "tubeless"
    ], 
    "beelssw": [
        "webless"
    ], 
    "beelst": [
        "betels"
    ], 
    "beelstu": [
        "elsebut"
    ], 
    "beelsv": [
        "bevels"
    ], 
    "beelsz": [
        "bezels"
    ], 
    "beelt": [
        "betel"
    ], 
    "beeltuz": [
        "zetulbe"
    ], 
    "beelu": [
        "bleue"
    ], 
    "beelv": [
        "bevel"
    ], 
    "beelz": [
        "bezel"
    ], 
    "beem": [
        "embe"
    ], 
    "beemmnnor": [
        "nonmember"
    ], 
    "beemmnnors": [
        "nonmembers"
    ], 
    "beemmnnostt": [
        "entombments"
    ], 
    "beemmnnott": [
        "entombment"
    ], 
    "beemmnossst": [
        "embossments"
    ], 
    "beemmnosst": [
        "embossment"
    ], 
    "beemmr": [
        "member"
    ], 
    "beemmrs": [
        "members"
    ], 
    "beemnnty": [
        "bennetmy"
    ], 
    "beemnorsss": [
        "sombreness", 
        "somberness"
    ], 
    "beemnorsv": [
        "novembers"
    ], 
    "beemnorv": [
        "november"
    ], 
    "beemnrrsu": [
        "numberers", 
        "renumbers"
    ], 
    "beemnrru": [
        "renumber", 
        "numberer"
    ], 
    "beemorss": [
        "embosser"
    ], 
    "beemorsss": [
        "embossers"
    ], 
    "beemorsw": [
        "embowers"
    ], 
    "beemorw": [
        "embower"
    ], 
    "beemosss": [
        "embosses"
    ], 
    "beemr": [
        "ember"
    ], 
    "beemrs": [
        "embers"
    ], 
    "beemrsssu": [
        "submerses"
    ], 
    "beemrssu": [
        "submerse"
    ], 
    "beemrsu": [
        "burmese"
    ], 
    "beemssu": [
        "bemuses"
    ], 
    "beemsu": [
        "bemuse"
    ], 
    "been": [
        "bene", 
        "been"
    ], 
    "beennoossstuu": [
        "bounteousness"
    ], 
    "beennort": [
        "bretonne"
    ], 
    "beennotuv": [
        "benvenuto"
    ], 
    "beennotw": [
        "townbeen"
    ], 
    "beennst": [
        "bennets"
    ], 
    "beennt": [
        "bennet"
    ], 
    "beenoorrv": [
        "overborne"
    ], 
    "beenor": [
        "enrobe"
    ], 
    "beenorr": [
        "enrober"
    ], 
    "beenorrs": [
        "enrobers"
    ], 
    "beenors": [
        "enrobes"
    ], 
    "beenorsss": [
        "soberness"
    ], 
    "beenorsstxy": [
        "sentryboxes"
    ], 
    "beenorstu": [
        "tenebrous"
    ], 
    "beenortt": [
        "nobetter"
    ], 
    "beenortv": [
        "verboten"
    ], 
    "beenossstu": [
        "obtuseness"
    ], 
    "beenosst": [
        "bonesets"
    ], 
    "beenost": [
        "boneset"
    ], 
    "beenqrsssuu": [
        "brusqueness"
    ], 
    "beenqsstuu": [
        "subsequent"
    ], 
    "beenrsttu": [
        "brunettes"
    ], 
    "beenrstw": [
        "bestrewn"
    ], 
    "beenrtt": [
        "bettern"
    ], 
    "beenrttu": [
        "brunette"
    ], 
    "beens": [
        "benes"
    ], 
    "beensstu": [
        "subteens"
    ], 
    "beenstu": [
        "subteen", 
        "steuben"
    ], 
    "beeooprrsstu": [
        "obstreperous"
    ], 
    "beeoorrv": [
        "overbore"
    ], 
    "beeoorstt": [
        "beetroots"
    ], 
    "beeoortt": [
        "beetroot"
    ], 
    "beeoost": [
        "bootees"
    ], 
    "beeoot": [
        "bootee"
    ], 
    "beeoppprx": [
        "pepperbox"
    ], 
    "beeopprsy": [
        "presbyope"
    ], 
    "beeoprr": [
        "reprobe"
    ], 
    "beeoprrs": [
        "reprobes"
    ], 
    "beeorrs": [
        "soberer"
    ], 
    "beeorrssv": [
        "observers"
    ], 
    "beeorrsu": [
        "bourrees"
    ], 
    "beeorrsv": [
        "observer"
    ], 
    "beeorru": [
        "bourree"
    ], 
    "beeorsst": [
        "soberest"
    ], 
    "beeorssttu": [
        "soubrettes"
    ], 
    "beeorsstu": [
        "tuberoses"
    ], 
    "beeorssv": [
        "obverses", 
        "observes"
    ], 
    "beeorsttu": [
        "soubrette"
    ], 
    "beeorstu": [
        "tuberose"
    ], 
    "beeorsv": [
        "obverse", 
        "observe", 
        "verbose"
    ], 
    "beeorswy": [
        "eyebrows"
    ], 
    "beeorsy": [
        "obeyers"
    ], 
    "beeortx": [
        "treebox"
    ], 
    "beeorwy": [
        "eyebrow"
    ], 
    "beeory": [
        "obeyer"
    ], 
    "beeos": [
        "obese"
    ], 
    "beeossss": [
        "obsesses"
    ], 
    "beep": [
        "beep"
    ], 
    "beeprrssty": [
        "presbyters"
    ], 
    "beeprrsty": [
        "presbyter"
    ], 
    "beeprrstyy": [
        "presbytery"
    ], 
    "beeprrsu": [
        "superber"
    ], 
    "beeps": [
        "beeps"
    ], 
    "beeptw": [
        "bewept"
    ], 
    "beeqsstu": [
        "bequests"
    ], 
    "beeqstu": [
        "bequest"
    ], 
    "beer": [
        "beer"
    ], 
    "beerrsstuv": [
        "subverters"
    ], 
    "beerrsttu": [
        "rebutters"
    ], 
    "beerrstuv": [
        "subverter"
    ], 
    "beerrsv": [
        "reverbs"
    ], 
    "beerrsw": [
        "brewers"
    ], 
    "beerrttu": [
        "rebutter"
    ], 
    "beerrv": [
        "reverb"
    ], 
    "beerrw": [
        "brewer"
    ], 
    "beerrwy": [
        "brewery"
    ], 
    "beers": [
        "beers"
    ], 
    "beersssttu": [
        "buttresses"
    ], 
    "beersstty": [
        "bystreets"
    ], 
    "beersstw": [
        "websters", 
        "bestrews"
    ], 
    "beerssu": [
        "rebuses"
    ], 
    "beerst": [
        "berets"
    ], 
    "beerstt": [
        "betters"
    ], 
    "beersttu": [
        "burettes"
    ], 
    "beerstty": [
        "bystreet"
    ], 
    "beerstv": [
        "brevets"
    ], 
    "beerstw": [
        "webster", 
        "bestrew"
    ], 
    "beersv": [
        "breves"
    ], 
    "beersw": [
        "webers"
    ], 
    "beert": [
        "beret"
    ], 
    "beertt": [
        "better"
    ], 
    "beerttu": [
        "burette"
    ], 
    "beertv": [
        "brevet"
    ], 
    "beeru": [
        "beure"
    ], 
    "beerv": [
        "breve"
    ], 
    "beerw": [
        "weber"
    ], 
    "beery": [
        "beery"
    ], 
    "beeryz": [
        "breezy"
    ], 
    "bees": [
        "bees"
    ], 
    "beess": [
        "besse"
    ], 
    "beesst": [
        "besets"
    ], 
    "beest": [
        "beset", 
        "betes", 
        "beets"
    ], 
    "beestuyy": [
        "yeyesbut"
    ], 
    "beet": [
        "beet", 
        "bete"
    ]
}