{
    "cfhhiimoorsty": [
        "ichthyosiform"
    ], 
    "cfhhissu": [
        "fishsuch"
    ], 
    "cfhiinoo": [
        "finochio"
    ], 
    "cfhiinoor": [
        "honorific"
    ], 
    "cfhiinoors": [
        "honorifics"
    ], 
    "cfhiinoos": [
        "finochios"
    ], 
    "cfhiiorr": [
        "horrific"
    ], 
    "cfhikoprst": [
        "pitchforks"
    ], 
    "cfhikoprt": [
        "pitchfork"
    ], 
    "cfhikors": [
        "rockfish"
    ], 
    "cfhil": [
        "filch"
    ], 
    "cfhiln": [
        "flinch"
    ], 
    "cfhilt": [
        "flitch"
    ], 
    "cfhin": [
        "finch"
    ], 
    "cfhiosw": [
        "cowfish"
    ], 
    "cfhisstu": [
        "fistsuch"
    ], 
    "cfhisu": [
        "fichus"
    ], 
    "cfhiu": [
        "fichu"
    ], 
    "cfhkoooprs": [
        "shockproof"
    ], 
    "cfhlmooorr": [
        "chloroform"
    ], 
    "cfhlmooorrs": [
        "chloroforms"
    ], 
    "cfhoooprr": [
        "porchroof"
    ], 
    "cfhooprrsu": [
        "crushproof"
    ]
}