{
    "cfiiilnnost": [
        "inflictions"
    ], 
    "cfiiilnnot": [
        "infliction"
    ], 
    "cfiiilosttuy": [
        "fictitiously"
    ], 
    "cfiiiosttu": [
        "fictitious"
    ], 
    "cfiiivv": [
        "vivific"
    ], 
    "cfiiknnqu": [
        "finnquick"
    ], 
    "cfiiknny": [
        "finnicky"
    ], 
    "cfiikny": [
        "finicky"
    ], 
    "cfiilm": [
        "filmic"
    ], 
    "cfiilmmor": [
        "microfilm"
    ], 
    "cfiilmmors": [
        "microfilms"
    ], 
    "cfiilmnnottuu": [
        "multifunction"
    ], 
    "cfiilnopru": [
        "unprolific"
    ], 
    "cfiilnort": [
        "inflictor"
    ], 
    "cfiilnst": [
        "inflicts"
    ], 
    "cfiilnt": [
        "inflict"
    ], 
    "cfiilopr": [
        "prolific"
    ], 
    "cfiimno": [
        "omnific"
    ], 
    "cfiimnos": [
        "somnific"
    ], 
    "cfiinnnoot": [
        "nonfiction"
    ], 
    "cfiinorst": [
        "frictions"
    ], 
    "cfiinort": [
        "friction"
    ], 
    "cfiinost": [
        "fictions"
    ], 
    "cfiinot": [
        "fiction"
    ], 
    "cfiinu": [
        "unific"
    ], 
    "cfiinyz": [
        "zincify"
    ], 
    "cfiiooprs": [
        "soporific"
    ], 
    "cfiiooprss": [
        "soporifics"
    ], 
    "cfiirsttuu": [
        "futuristic"
    ], 
    "cfiist": [
        "fistic"
    ], 
    "cfiity": [
        "citify"
    ], 
    "cfikl": [
        "flick"
    ], 
    "cfikllnost": [
        "flintlocks"
    ], 
    "cfikllnot": [
        "flintlock"
    ], 
    "cfiklloor": [
        "folkloric"
    ], 
    "cfiklory": [
        "frolicky"
    ], 
    "cfikls": [
        "flicks"
    ], 
    "cfilmoor": [
        "coliform"
    ], 
    "cfilmoors": [
        "coliforms"
    ], 
    "cfilnsuuu": [
        "funiculus"
    ], 
    "cfilo": [
        "folic"
    ], 
    "cfiloooprssstu": [
        "fluoroscopists"
    ], 
    "cfiloooprsstu": [
        "fluoroscopist"
    ], 
    "cfilor": [
        "frolic"
    ], 
    "cfilors": [
        "frolics"
    ], 
    "cfilrsuu": [
        "sulfuric"
    ], 
    "cfilst": [
        "clifts"
    ], 
    "cfilt": [
        "clift"
    ], 
    "cfimmnnnooors": [
        "nonconformism"
    ], 
    "cfimmnoors": [
        "conformism"
    ], 
    "cfimmoorr": [
        "microform"
    ], 
    "cfimmoorrs": [
        "microforms"
    ], 
    "cfimnnnooorsst": [
        "nonconformists"
    ], 
    "cfimnnnooorst": [
        "nonconformist"
    ], 
    "cfimnnnooorty": [
        "nonconformity"
    ], 
    "cfimnoorr": [
        "confirmor"
    ], 
    "cfimnoorsst": [
        "conformists"
    ], 
    "cfimnoorst": [
        "conformist"
    ], 
    "cfimnoorty": [
        "conformity"
    ], 
    "cfimnor": [
        "confirm"
    ], 
    "cfimnors": [
        "confirms"
    ], 
    "cfimnorsu": [
        "unciforms"
    ], 
    "cfimnoru": [
        "cuniform"
    ], 
    "cfimor": [
        "formic"
    ], 
    "cfimost": [
        "comfits"
    ], 
    "cfimot": [
        "comfit"
    ], 
    "cfinnoossu": [
        "confusions"
    ], 
    "cfinnoosu": [
        "confusion"
    ], 
    "cfinnostu": [
        "functions"
    ], 
    "cfinnotu": [
        "function"
    ], 
    "cfinory": [
        "cornify"
    ], 
    "cfio": [
        "foci", 
        "coif"
    ], 
    "cfioorrsuuu": [
        "curiousfour"
    ], 
    "cfiorsy": [
        "scorify"
    ], 
    "cfiort": [
        "fricot"
    ], 
    "cfios": [
        "coifs"
    ], 
    "cfisstu": [
        "fustics"
    ], 
    "cfistu": [
        "fustic"
    ]
}