{
    "coo": [
        "coo"
    ], 
    "cooopsty": [
        "otoscopy"
    ], 
    "coop": [
        "poco", 
        "coop"
    ], 
    "cooprrrtu": [
        "corruptor"
    ], 
    "cooprrst": [
        "proctors"
    ], 
    "cooprrt": [
        "proctor"
    ], 
    "cooprstu": [
        "outcrops"
    ], 
    "cooprtu": [
        "outcrop"
    ], 
    "coops": [
        "scopo", 
        "scoop", 
        "coops"
    ], 
    "coopss": [
        "scoops"
    ], 
    "coopst": [
        "coopts"
    ], 
    "coopstu": [
        "octopus", 
        "copouts"
    ], 
    "coopt": [
        "coopt"
    ], 
    "cooptu": [
        "copout"
    ], 
    "coopwx": [
        "cowpox"
    ], 
    "coort": [
        "corto"
    ], 
    "coos": [
        "coos"
    ], 
    "coosst": [
        "scoots"
    ], 
    "coost": [
        "scoot", 
        "coots"
    ], 
    "coostuu": [
        "coustou"
    ], 
    "coot": [
        "coot"
    ]
}