{
    "ehi": [
        "hie", 
        "hei"
    ], 
    "ehiii": [
        "iiihe"
    ], 
    "ehiiiilnst": [
        "nihilities"
    ], 
    "ehiiiilw": [
        "iiiwhile"
    ], 
    "ehiiillopppsu": [
        "louisphilippe"
    ], 
    "ehiiilmstu": [
        "humilities"
    ], 
    "ehiiilnppp": [
        "philippine"
    ], 
    "ehiiilnppps": [
        "philippines"
    ], 
    "ehiiilnpsst": [
        "philistines"
    ], 
    "ehiiilnpst": [
        "philistine"
    ], 
    "ehiiilosstt": [
        "hostilities"
    ], 
    "ehiiimort": [
        "iiimother"
    ], 
    "ehiiinoopsstttvy": [
        "photosensitivity"
    ], 
    "ehiiinopssttvyy": [
        "hyposensitivity"
    ], 
    "ehiiipsx": [
        "pixieish"
    ], 
    "ehiiit": [
        "iiithe"
    ], 
    "ehiiitv": [
        "viiithe"
    ], 
    "ehiiitvx": [
        "xviiithe"
    ], 
    "ehiiitx": [
        "xiiithe"
    ], 
    "ehiiity": [
        "iiithey"
    ], 
    "ehiiklns": [
        "helsinki"
    ], 
    "ehiiklnstty": [
        "kittenishly"
    ], 
    "ehiikmrrss": [
        "skirmisher"
    ], 
    "ehiikmrrsss": [
        "skirmishers"
    ], 
    "ehiikmrsss": [
        "skirmishes"
    ], 
    "ehiiknnpsss": [
        "pinkishness"
    ], 
    "ehiiknsssstt": [
        "skittishness"
    ], 
    "ehiiknstt": [
        "kittenish"
    ], 
    "ehiikssw": [
        "whiskies"
    ], 
    "ehiillnss": [
        "hilliness"
    ], 
    "ehiillopsstww": [
        "willothewisps"
    ], 
    "ehiillopstww": [
        "willothewisp"
    ], 
    "ehiillppss": [
        "phillipses"
    ], 
    "ehiillr": [
        "hillier"
    ], 
    "ehiillst": [
        "hilliest"
    ], 
    "ehiillstttx": [
        "sixthlittle"
    ], 
    "ehiilmooprst": [
        "heliotropism"
    ], 
    "ehiilmos": [
        "homilies"
    ], 
    "ehiilmrssstv": [
        "silversmiths"
    ], 
    "ehiilmrsstv": [
        "silversmith"
    ], 
    "ehiilmrst": [
        "hitlerism"
    ], 
    "ehiilmsu": [
        "humilies"
    ], 
    "ehiilnp": [
        "hipline"
    ], 
    "ehiilnqrsu": [
        "relinquish"
    ], 
    "ehiilnqu": [
        "nihilque"
    ], 
    "ehiilnsvxy": [
        "vixenishly"
    ], 
    "ehiilppp": [
        "philippe"
    ], 
    "ehiilppps": [
        "philippes"
    ], 
    "ehiilpsssy": [
        "syphilises"
    ], 
    "ehiilrrw": [
        "whirlier"
    ], 
    "ehiilrstw": [
        "whirliest"
    ], 
    "ehiilrsv": [
        "liverish"
    ], 
    "ehiilrsw": [
        "whirlies"
    ], 
    "ehiimmss": [
        "shimmies"
    ], 
    "ehiimnors": [
        "heroinism"
    ], 
    "ehiimnorsw": [
        "irishwomen"
    ], 
    "ehiimnos": [
        "hominies"
    ], 
    "ehiimnpsss": [
        "impishness"
    ], 
    "ehiimnrs": [
        "irishmen"
    ], 
    "ehiimoprsv": [
        "impoverish"
    ], 
    "ehiimort": [
        "iimother"
    ], 
    "ehiimostt": [
        "timothies"
    ], 
    "ehiimpprsu": [
        "umpireship"
    ], 
    "ehiimprrs": [
        "shrimpier"
    ], 
    "ehiimprsst": [
        "shrimpiest"
    ], 
    "ehiimpst": [
        "mephitis"
    ], 
    "ehiimsst": [
        "smithies"
    ], 
    "ehiimssw": [
        "whimsies"
    ], 
    "ehiinnoss": [
        "inhesions"
    ], 
    "ehiinnprsst": [
        "internships"
    ], 
    "ehiinnprst": [
        "internship"
    ], 
    "ehiinnrss": [
        "inshrines"
    ], 
    "ehiinnrtty": [
        "thirtynine"
    ], 
    "ehiinnrw": [
        "whinnier"
    ], 
    "ehiinns": [
        "hinnies"
    ], 
    "ehiinnss": [
        "shinnies"
    ], 
    "ehiinnsss": [
        "shininess"
    ], 
    "ehiinnstw": [
        "whinniest"
    ], 
    "ehiinnsw": [
        "whinnies"
    ], 
    "ehiinorrst": [
        "inheritors"
    ], 
    "ehiinorrt": [
        "inheritor"
    ], 
    "ehiinostv": [
        "visionthe"
    ], 
    "ehiinpprsw": [
        "whippersin"
    ], 
    "ehiinprst": [
        "nephritis"
    ], 
    "ehiinpsst": [
        "pithiness"
    ], 
    "ehiinrs": [
        "shinier"
    ], 
    "ehiinrssstt": [
        "thirstiness"
    ], 
    "ehiinrst": [
        "inherits"
    ], 
    "ehiinrt": [
        "inherit"
    ], 
    "ehiinrw": [
        "whinier"
    ], 
    "ehiinsst": [
        "shiniest"
    ], 
    "ehiinstw": [
        "whiniest"
    ], 
    "ehiinsvx": [
        "vixenish"
    ], 
    "ehiiooppprrrsst": [
        "proprietorships"
    ], 
    "ehiiooppprrrst": [
        "proprietorship"
    ], 
    "ehiiopprrsssuv": [
        "supervisorship"
    ], 
    "ehiioprssst": [
        "sophistries"
    ], 
    "ehiioqrsstu": [
        "historiques"
    ], 
    "ehiiorsst": [
        "histories"
    ], 
    "ehiiorst": [
        "histoire"
    ], 
    "ehiipp": [
        "hippie"
    ], 
    "ehiippr": [
        "hippier"
    ], 
    "ehiipprw": [
        "whippier"
    ], 
    "ehiipps": [
        "hippies"
    ], 
    "ehiippstw": [
        "whippiest"
    ], 
    "ehiiprsv": [
        "viperish"
    ], 
    "ehiiprt": [
        "pithier"
    ], 
    "ehiipstt": [
        "pithiest"
    ], 
    "ehiiqrssu": [
        "squishier"
    ], 
    "ehiiqssstu": [
        "squishiest"
    ], 
    "ehiirrst": [
        "shirtier"
    ], 
    "ehiirrstt": [
        "thirstier"
    ], 
    "ehiirrtx": [
        "heritrix"
    ], 
    "ehiirsstt": [
        "shirtiest"
    ], 
    "ehiirssttt": [
        "thirstiest"
    ], 
    "ehiirssttz": [
        "zitherists"
    ], 
    "ehiirssw": [
        "swishier"
    ], 
    "ehiirstt": [
        "thirties"
    ], 
    "ehiirsttz": [
        "zitherist"
    ], 
    "ehiirstv": [
        "shiverit"
    ], 
    "ehiirtw": [
        "withier"
    ], 
    "ehiissstw": [
        "swishiest"
    ], 
    "ehiissttx": [
        "sixtieths"
    ], 
    "ehiisttx": [
        "sixtieth"
    ], 
    "ehiistw": [
        "whities", 
        "withies"
    ], 
    "ehiit": [
        "iithe"
    ], 
    "ehiitv": [
        "viithe"
    ], 
    "ehiitvx": [
        "xviithe"
    ], 
    "ehiitx": [
        "xiithe"
    ], 
    "ehiitxx": [
        "xxiithe"
    ], 
    "ehijnno": [
        "johnnie"
    ], 
    "ehijnnos": [
        "johnnies"
    ], 
    "ehijsw": [
        "jewish"
    ], 
    "ehik": [
        "hike"
    ], 
    "ehikkoopsy": [
        "hokypokies"
    ], 
    "ehikkss": [
        "kishkes"
    ], 
    "ehiklnor": [
        "hornlike"
    ], 
    "ehiklnortw": [
        "kenilworth"
    ], 
    "ehiklnos": [
        "sinkhole"
    ], 
    "ehiklnoss": [
        "sinkholes"
    ], 
    "ehiklortz": [
        "kilohertz"
    ], 
    "ehiklosy": [
        "yokelish"
    ], 
    "ehiklru": [
        "hulkier"
    ], 
    "ehikmnnosss": [
        "monkishness"
    ], 
    "ehikmnot": [
        "homeknit"
    ], 
    "ehikmnst": [
        "methinks"
    ], 
    "ehikmrtu": [
        "turkheim"
    ], 
    "ehikmv": [
        "mikveh"
    ], 
    "ehikno": [
        "honkie"
    ], 
    "ehiknos": [
        "honkies"
    ], 
    "ehiknprssu": [
        "shunpikers"
    ], 
    "ehiknprsu": [
        "shunpiker"
    ], 
    "ehiknpssu": [
        "shunpikes"
    ], 
    "ehiknpsu": [
        "shunpike"
    ], 
    "ehiknrrs": [
        "shrinker"
    ], 
    "ehiknrrss": [
        "shrinkers"
    ], 
    "ehiknrst": [
        "thinkers", 
        "rethinks"
    ], 
    "ehiknrt": [
        "rethink", 
        "thinker"
    ], 
    "ehiknss": [
        "knishes"
    ], 
    "ehiknsssu": [
        "huskiness"
    ], 
    "ehikoor": [
        "hookier"
    ], 
    "ehikoos": [
        "hookies"
    ], 
    "ehikor": [
        "hokier"
    ], 
    "ehikost": [
        "hokiest"
    ], 
    "ehikprs": [
        "perkish"
    ], 
    "ehikr": [
        "hiker"
    ], 
    "ehikrrs": [
        "shirker"
    ], 
    "ehikrrss": [
        "shirkers"
    ], 
    "ehikrs": [
        "shrike", 
        "hikers", 
        "shriek"
    ], 
    "ehikrss": [
        "shrieks", 
        "shrikes"
    ], 
    "ehikrssw": [
        "whiskers"
    ], 
    "ehikrsu": [
        "huskier"
    ], 
    "ehikrsw": [
        "whisker"
    ], 
    "ehikrswy": [
        "whiskery"
    ], 
    "ehikrsy": [
        "shrieky"
    ], 
    "ehiks": [
        "hikes", 
        "sheik"
    ], 
    "ehikss": [
        "sheiks"
    ], 
    "ehiksss": [
        "shikses"
    ], 
    "ehiksstu": [
        "huskiest"
    ], 
    "ehikssu": [
        "huskies"
    ], 
    "ehiksswy": [
        "whiskeys"
    ], 
    "ehikswy": [
        "whiskey"
    ], 
    "ehil": [
        "heil", 
        "elhi"
    ], 
    "ehilllmo": [
        "molehill"
    ], 
    "ehilllmos": [
        "molehills"
    ], 
    "ehillmop": [
        "philomel"
    ], 
    "ehillmops": [
        "philomels"
    ], 
    "ehillno": [
        "hellion"
    ], 
    "ehillnos": [
        "hellions"
    ], 
    "ehillnowy": [
        "honeywill"
    ], 
    "ehillnrsss": [
        "shrillness"
    ], 
    "ehilloo": [
        "oilhole"
    ], 
    "ehillooprssstt": [
        "holsterpistols"
    ], 
    "ehillooprsstt": [
        "holsterpistol"
    ], 
    "ehillooqstuyy": [
        "soliloquythey"
    ], 
    "ehillos": [
        "hollies"
    ], 
    "ehillosstu": [
        "stillhouse"
    ], 
    "ehillosty": [
        "hostilely"
    ], 
    "ehilloswy": [
        "yellowish"
    ], 
    "ehillr": [
        "hiller"
    ], 
    "ehillrrs": [
        "shriller"
    ], 
    "ehillrrst": [
        "thrillers"
    ], 
    "ehillrrt": [
        "thriller"
    ], 
    "ehillrs": [
        "hillers"
    ], 
    "ehillrsst": [
        "shrillest"
    ], 
    "ehillsst": [
        "hiltless"
    ], 
    "ehillsvy": [
        "elvishly"
    ], 
    "ehillty": [
        "lithely"
    ], 
    "ehilmmnosty": [
        "semimonthly"
    ], 
    "ehilmnop": [
        "philemon"
    ], 
    "ehilmnos": [
        "lemonish"
    ], 
    "ehilmnost": [
        "monthlies"
    ], 
    "ehilmnsssu": [
        "mulishness"
    ], 
    "ehilmoor": [
        "heirloom"
    ], 
    "ehilmoors": [
        "heirlooms"
    ], 
    "ehilmoostvy": [
        "ivtholomyes"
    ], 
    "ehilmoott": [
        "lithotome"
    ], 
    "ehilmopsty": [
        "polytheism"
    ], 
    "ehilmrsst": [
        "mirthless"
    ], 
    "ehilmsu": [
        "heliums"
    ], 
    "ehilmu": [
        "helium"
    ], 
    "ehilnnossu": [
        "unholiness"
    ], 
    "ehilnoorttwy": [
        "noteworthily"
    ], 
    "ehilnop": [
        "pinhole"
    ], 
    "ehilnoprstu": [
        "neutrophils"
    ], 
    "ehilnoprtu": [
        "neutrophil"
    ], 
    "ehilnops": [
        "pinholes"
    ], 
    "ehilnoru": [
        "unholier"
    ], 
    "ehilnoss": [
        "holiness"
    ], 
    "ehilnossstu": [
        "loutishness"
    ], 
    "ehilnosst": [
        "holsteins"
    ], 
    "ehilnost": [
        "holstein", 
        "neoliths"
    ], 
    "ehilnostu": [
        "unholiest"
    ], 
    "ehilnostx": [
        "xenoliths"
    ], 
    "ehilnosuy": [
        "heinously"
    ], 
    "ehilnot": [
        "neolith", 
        "hotline"
    ], 
    "ehilnotx": [
        "xenolith"
    ], 
    "ehilnssssttu": [
        "sluttishness"
    ], 
    "ehilnssssty": [
        "stylishness"
    ], 
    "ehilnssssu": [
        "slushiness"
    ], 
    "ehilo": [
        "helio"
    ], 
    "ehilooprssst": [
        "horsepistols"
    ], 
    "ehilooprsux": [
        "xerophilous"
    ], 
    "ehiloopsstu": [
        "pilothouses"
    ], 
    "ehiloopst": [
        "opheltios"
    ], 
    "ehiloopstu": [
        "pilothouse"
    ], 
    "ehiloopsz": [
        "zoophiles"
    ], 
    "ehiloprs": [
        "polisher"
    ], 
    "ehiloprss": [
        "polishers"
    ], 
    "ehiloprst": [
        "heliports"
    ], 
    "ehiloprt": [
        "heliport"
    ], 
    "ehilopss": [
        "polishes"
    ], 
    "ehilopsst": [
        "helistops"
    ], 
    "ehilopsstty": [
        "polytheists"
    ], 
    "ehilopst": [
        "helistop"
    ], 
    "ehilopstty": [
        "polytheist"
    ], 
    "ehilopt": [
        "hoplite"
    ], 
    "ehilor": [
        "holier"
    ], 
    "ehilorss": [
        "sloshier"
    ], 
    "ehilorty": [
        "rhyolite"
    ], 
    "ehilos": [
        "helios", 
        "holies"
    ], 
    "ehilossst": [
        "sloshiest"
    ], 
    "ehilosst": [
        "hostiles"
    ], 
    "ehilost": [
        "hostile", 
        "holiest", 
        "eoliths"
    ], 
    "ehilot": [
        "eolith"
    ], 
    "ehilprrsu": [
        "rulership"
    ], 
    "ehilprst": [
        "philtres", 
        "philters"
    ], 
    "ehilprsu": [
        "plushier"
    ], 
    "ehilprsuuz": [
        "sulphurize"
    ], 
    "ehilprt": [
        "philtre", 
        "philter"
    ], 
    "ehilpss": [
        "hipless"
    ], 
    "ehilpsstu": [
        "plushiest"
    ], 
    "ehilpstty": [
        "pettishly"
    ], 
    "ehilrrsw": [
        "whirlers"
    ], 
    "ehilrrw": [
        "whirler"
    ], 
    "ehilrs": [
        "relish"
    ], 
    "ehilrsst": [
        "slithers"
    ], 
    "ehilrsstw": [
        "whistlers"
    ], 
    "ehilrssu": [
        "slushier"
    ], 
    "ehilrssv": [
        "shrivels"
    ], 
    "ehilrst": [
        "slither"
    ], 
    "ehilrsttw": [
        "whittlers"
    ], 
    "ehilrstw": [
        "whistler"
    ], 
    "ehilrsty": [
        "slithery"
    ], 
    "ehilrsv": [
        "shrivel"
    ], 
    "ehilrsy": [
        "shirley"
    ], 
    "ehilrt": [
        "lither", 
        "hitler"
    ], 
    "ehilrttw": [
        "whittler"
    ], 
    "ehilrv": [
        "lhiver"
    ], 
    "ehils": [
        "heils"
    ], 
    "ehilssstu": [
        "slushiest"
    ], 
    "ehilsssw": [
        "wishless"
    ], 
    "ehilsst": [
        "hitless"
    ], 
    "ehilsstt": [
        "thistles"
    ], 
    "ehilsstw": [
        "whistles"
    ], 
    "ehilstt": [
        "lithest", 
        "thistle"
    ], 
    "ehilsttw": [
        "whittles"
    ], 
    "ehilstw": [
        "whistle"
    ], 
    "ehilstx": [
        "sixthle"
    ], 
    "ehilsv": [
        "elvish"
    ], 
    "ehilsw": [
        "whiles"
    ], 
    "ehilt": [
        "lithe"
    ], 
    "ehilttw": [
        "whittle"
    ], 
    "ehiltwy": [
        "whitely"
    ], 
    "ehilvwy": [
        "livewhy"
    ], 
    "ehilw": [
        "while"
    ], 
    "ehilx": [
        "helix"
    ], 
    "ehimmno": [
        "hominem"
    ], 
    "ehimmnoost": [
        "monotheism"
    ], 
    "ehimmnoosy": [
        "homonymies"
    ], 
    "ehimmooorst": [
        "homoerotism"
    ], 
    "ehimmoprtu": [
        "promethium"
    ], 
    "ehimmps": [
        "memphis"
    ], 
    "ehimmrrtu": [
        "thrummier"
    ], 
    "ehimmrs": [
        "shimmer"
    ], 
    "ehimmrss": [
        "shimmers"
    ], 
    "ehimmrsttu": [
        "thrummiest"
    ], 
    "ehimmrsy": [
        "shimmery"
    ], 
    "ehimms": [
        "immesh"
    ], 
    "ehimnnoors": [
        "moonshiner"
    ], 
    "ehimnnoorss": [
        "moonshiners"
    ], 
    "ehimnnoos": [
        "moonshine"
    ], 
    "ehimnnorsstu": [
        "nourishments"
    ], 
    "ehimnnorstu": [
        "nourishment"
    ], 
    "ehimnnpsstu": [
        "punishments"
    ], 
    "ehimnnpstu": [
        "punishment"
    ], 
    "ehimnoosstt": [
        "monotheists"
    ], 
    "ehimnoostt": [
        "monotheist"
    ], 
    "ehimnootx": [
        "hemotoxin"
    ], 
    "ehimnopr": [
        "morphine"
    ], 
    "ehimnoprs": [
        "morphines"
    ], 
    "ehimnopssy": [
        "symphonies"
    ], 
    "ehimnoss": [
        "hominess"
    ], 
    "ehimnps": [
        "shipmen"
    ], 
    "ehimnpsst": [
        "shipments"
    ], 
    "ehimnpst": [
        "shipment"
    ], 
    "ehimnr": [
        "menhir"
    ], 
    "ehimnrs": [
        "menhirs"
    ], 
    "ehimnrsu": [
        "rheniums"
    ], 
    "ehimnrtuu": [
        "ruthenium"
    ], 
    "ehimnru": [
        "inhumer", 
        "rhenium"
    ], 
    "ehimns": [
        "inmesh"
    ], 
    "ehimnsssu": [
        "mushiness"
    ], 
    "ehimnsty": [
        "thymines"
    ], 
    "ehimnsu": [
        "inhumes"
    ], 
    "ehimnty": [
        "thymine"
    ], 
    "ehimnu": [
        "inhume"
    ], 
    "ehimoosst": [
        "smoothies"
    ], 
    "ehimoost": [
        "smoothie"
    ], 
    "ehimor": [
        "homier"
    ], 
    "ehimorrsstt": [
        "thermistors"
    ], 
    "ehimorrstt": [
        "thermistor"
    ], 
    "ehimors": [
        "heroism"
    ], 
    "ehimorss": [
        "heroisms"
    ], 
    "ehimorsst": [
        "isotherms"
    ], 
    "ehimorst": [
        "isotherm"
    ], 
    "ehimorsz": [
        "rhizomes"
    ], 
    "ehimort": [
        "mothier"
    ], 
    "ehimortu": [
        "mouthier"
    ], 
    "ehimorz": [
        "rhizome"
    ], 
    "ehimost": [
        "homiest"
    ], 
    "ehimosttu": [
        "mouthiest"
    ], 
    "ehimprrs": [
        "shrimper"
    ], 
    "ehimprrss": [
        "shrimpers"
    ], 
    "ehimprsu": [
        "murphies"
    ], 
    "ehimprsw": [
        "whimpers"
    ], 
    "ehimpru": [
        "humpier"
    ], 
    "ehimprw": [
        "whimper"
    ], 
    "ehimrrty": [
        "hermitry"
    ], 
    "ehimrs": [
        "rheims"
    ], 
    "ehimrst": [
        "hermits"
    ], 
    "ehimrsttu": [
        "trithemus"
    ], 
    "ehimrsu": [
        "mushier"
    ], 
    "ehimrt": [
        "hermit"
    ], 
    "ehimrty": [
        "thymier"
    ], 
    "ehimru": [
        "humeri"
    ], 
    "ehimssstu": [
        "isthmuses"
    ], 
    "ehimsst": [
        "theisms", 
        "sithems"
    ], 
    "ehimsstu": [
        "mushiest"
    ], 
    "ehimst": [
        "themis", 
        "theism"
    ], 
    "ehimswy": [
        "whimsey"
    ], 
    "ehimt": [
        "themi"
    ], 
    "ehinnoopsty": [
        "hypotension"
    ], 
    "ehinnopss": [
        "phoniness"
    ], 
    "ehinnorsstuw": [
        "unworthiness"
    ], 
    "ehinnostw": [
        "nonwhites"
    ], 
    "ehinnotw": [
        "nonwhite"
    ], 
    "ehinnrst": [
        "thinners"
    ], 
    "ehinnrt": [
        "thinner"
    ], 
    "ehinnsssu": [
        "sunshines"
    ], 
    "ehinnsst": [
        "thinness"
    ], 
    "ehinnssu": [
        "sunshine"
    ], 
    "ehinnstt": [
        "thinnest"
    ], 
    "ehinnsw": [
        "wennish"
    ], 
    "ehinnsy": [
        "shinney"
    ], 
    "ehinnt": [
        "inthen"
    ], 
    "ehinoopru": [
        "euphorion"
    ], 
    "ehinoopsuu": [
        "euphonious"
    ], 
    "ehinooqsstuw": [
        "questionshow"
    ], 
    "ehinoostv": [
        "vineshoot"
    ], 
    "ehinoppr": [
        "hornpipe"
    ], 
    "ehinopprs": [
        "hornpipes"
    ], 
    "ehinopr": [
        "phonier"
    ], 
    "ehinoprsst": [
        "thesprions"
    ], 
    "ehinoprssw": [
        "ownerships"
    ], 
    "ehinoprst": [
        "prisonthe"
    ], 
    "ehinoprsw": [
        "shipowner", 
        "ownership"
    ], 
    "ehinopry": [
        "hyperion"
    ], 
    "ehinops": [
        "phonies"
    ], 
    "ehinopssw": [
        "wineshops"
    ], 
    "ehinopst": [
        "phoniest"
    ], 
    "ehinopstyz": [
        "hypnotizes"
    ], 
    "ehinopsw": [
        "wineshop"
    ], 
    "ehinoptyz": [
        "hypnotize"
    ], 
    "ehinopx": [
        "phoenix"
    ], 
    "ehinoqstuwy": [
        "questionwhy"
    ], 
    "ehinor": [
        "heroin"
    ], 
    "ehinorr": [
        "hornier"
    ], 
    "ehinorrssstttuw": [
        "trustworthiness"
    ], 
    "ehinorrssu": [
        "nourishers"
    ], 
    "ehinorrsu": [
        "nourisher"
    ], 
    "ehinorrt": [
        "thornier"
    ], 
    "ehinorrtuw": [
        "unworthier"
    ], 
    "ehinors": [
        "inshore", 
        "heroins"
    ], 
    "ehinorsstw": [
        "worthiness"
    ], 
    "ehinorssu": [
        "nourishes"
    ], 
    "ehinorst": [
        "horniest"
    ], 
    "ehinorstt": [
        "thorniest"
    ], 
    "ehinorstuw": [
        "unworthies"
    ], 
    "ehinortty": [
        "thirtyone"
    ], 
    "ehinorv": [
        "hoverin"
    ], 
    "ehinosssw": [
        "showiness"
    ], 
    "ehinosstu": [
        "outshines"
    ], 
    "ehinostu": [
        "outshine"
    ], 
    "ehinosu": [
        "heinous"
    ], 
    "ehinpp": [
        "heppin"
    ], 
    "ehinprrty": [
        "pyrethrin"
    ], 
    "ehinprssu": [
        "punishers"
    ], 
    "ehinprsu": [
        "punisher"
    ], 
    "ehinpss": [
        "hipness"
    ], 
    "ehinpsssu": [
        "pushiness"
    ], 
    "ehinpssu": [
        "punishes"
    ], 
    "ehinpssx": [
        "sphinxes"
    ], 
    "ehinpx": [
        "phenix"
    ], 
    "ehinr": [
        "rhine", 
        "henri"
    ], 
    "ehinrs": [
        "shiner", 
        "shrine"
    ], 
    "ehinrss": [
        "shrines", 
        "shiners"
    ], 
    "ehinrssu": [
        "inrushes"
    ], 
    "ehinrst": [
        "hinters"
    ], 
    "ehinrstz": [
        "zitherns"
    ], 
    "ehinrsv": [
        "shriven"
    ], 
    "ehinrsw": [
        "whiners"
    ], 
    "ehinrt": [
        "hinter", 
        "theirn"
    ], 
    "ehinrtv": [
        "thriven"
    ], 
    "ehinrtz": [
        "zithern"
    ], 
    "ehinrw": [
        "whiner"
    ], 
    "ehins": [
        "shine", 
        "hines"
    ], 
    "ehinss": [
        "shines"
    ], 
    "ehinsssty": [
        "synthesis"
    ], 
    "ehinssuw": [
        "unwishes"
    ], 
    "ehinstw": [
        "whitens"
    ], 
    "ehinstz": [
        "zeniths"
    ], 
    "ehinsw": [
        "newish", 
        "whines"
    ], 
    "ehint": [
        "theni", 
        "thine"
    ], 
    "ehintt": [
        "thenit"
    ], 
    "ehintw": [
        "whiten"
    ], 
    "ehintwy": [
        "whitney"
    ], 
    "ehintz": [
        "zenith"
    ], 
    "ehinw": [
        "whine"
    ], 
    "ehinwy": [
        "whiney"
    ], 
    "ehiooprsstt": [
        "orthoepists"
    ], 
    "ehiooprstt": [
        "orthoepist"
    ], 
    "ehiooprstw": [
        "wirephotos"
    ], 
    "ehiooprtw": [
        "wirephoto"
    ], 
    "ehioors": [
        "hoosier"
    ], 
    "ehioorss": [
        "hoosiers"
    ], 
    "ehioortt": [
        "toothier"
    ], 
    "ehioosttt": [
        "toothiest"
    ], 
    "ehiopprrssw": [
        "worshippers"
    ], 
    "ehiopprrsw": [
        "worshipper"
    ], 
    "ehiopprrsy": [
        "porphyries"
    ], 
    "ehioppsu": [
        "eohippus"
    ], 
    "ehioprrssw": [
        "worshipers"
    ], 
    "ehioprrsty": [
        "prehistory"
    ], 
    "ehioprrsw": [
        "worshiper"
    ], 
    "ehioprssst": [
        "prosthesis"
    ], 
    "ehioprssttt": [
        "prosthetist"
    ], 
    "ehioprst": [
        "trophies"
    ], 
    "ehioprux": [
        "hurepoix"
    ], 
    "ehiopss": [
        "sophies"
    ], 
    "ehior": [
        "hiero"
    ], 
    "ehiorrs": [
        "horsier"
    ], 
    "ehiorrst": [
        "heritors"
    ], 
    "ehiorrt": [
        "heritor"
    ], 
    "ehiorrtw": [
        "worthier"
    ], 
    "ehiors": [
        "hosier", 
        "shorei"
    ], 
    "ehiorss": [
        "hosiers"
    ], 
    "ehiorssstw": [
        "sisterswho"
    ], 
    "ehiorsst": [
        "horsiest", 
        "hoisters", 
        "shorties"
    ], 
    "ehiorsstt": [
        "theorists"
    ], 
    "ehiorst": [
        "shoreit", 
        "shortie", 
        "hoister"
    ], 
    "ehiorstt": [
        "theorist"
    ], 
    "ehiorsttw": [
        "worthiest"
    ], 
    "ehiorstw": [
        "worthies"
    ], 
    "ehiorstwz": [
        "howitzers"
    ], 
    "ehiorsw": [
        "showier"
    ], 
    "ehiorsy": [
        "hosiery"
    ], 
    "ehiortt": [
        "totheri", 
        "otherit"
    ], 
    "ehiortwz": [
        "howitzer"
    ], 
    "ehios": [
        "hoise"
    ], 
    "ehiossstu": [
        "housesits"
    ], 
    "ehiosstu": [
        "housesit"
    ], 
    "ehiosstw": [
        "showiest"
    ], 
    "ehiosttuw": [
        "whiteouts"
    ], 
    "ehiosttuwy": [
        "yeswithout"
    ], 
    "ehiottuw": [
        "whiteout"
    ], 
    "ehippr": [
        "hipper"
    ], 
    "ehipprs": [
        "shipper"
    ], 
    "ehipprss": [
        "shippers"
    ], 
    "ehipprsw": [
        "whippers"
    ], 
    "ehipprw": [
        "whipper"
    ], 
    "ehippst": [
        "hippest"
    ], 
    "ehippstw": [
        "whippets"
    ], 
    "ehipptw": [
        "whippet"
    ], 
    "ehipqssuy": [
        "physiques"
    ], 
    "ehipqsuy": [
        "physique"
    ], 
    "ehiprs": [
        "perish", 
        "reship"
    ], 
    "ehiprss": [
        "reships"
    ], 
    "ehiprsst": [
        "hipsters"
    ], 
    "ehiprssw": [
        "whispers"
    ], 
    "ehiprst": [
        "hipster"
    ], 
    "ehiprstty": [
        "prettyish"
    ], 
    "ehiprsu": [
        "pushier"
    ], 
    "ehiprsw": [
        "whisper"
    ], 
    "ehiprswy": [
        "whispery"
    ], 
    "ehipss": [
        "pishes"
    ], 
    "ehipsst": [
        "thespis"
    ], 
    "ehipsstu": [
        "pushiest"
    ], 
    "ehipstt": [
        "pettish"
    ], 
    "ehipsty": [
        "pityshe"
    ], 
    "ehiqru": [
        "quhier"
    ], 
    "ehiqsssu": [
        "squishes"
    ], 
    "ehir": [
        "hire", 
        "heir"
    ], 
    "ehirr": [
        "hirer"
    ], 
    "ehirrrsu": [
        "hurriers"
    ], 
    "ehirrru": [
        "hurrier"
    ], 
    "ehirrs": [
        "hirers"
    ], 
    "ehirrsstt": [
        "thirsters"
    ], 
    "ehirrssv": [
        "shrivers"
    ], 
    "ehirrstt": [
        "thirster"
    ], 
    "ehirrstv": [
        "thrivers"
    ], 
    "ehirrstw": [
        "writhers"
    ], 
    "ehirrsu": [
        "hurries", 
        "rushier"
    ], 
    "ehirrsv": [
        "shriver"
    ], 
    "ehirrtv": [
        "thriver"
    ], 
    "ehirrtw": [
        "writher"
    ], 
    "ehirrty": [
        "thierry"
    ], 
    "ehirs": [
        "isher", 
        "shire", 
        "hires", 
        "shier", 
        "heirs"
    ], 
    "ehirss": [
        "hisser", 
        "shiers", 
        "shires"
    ], 
    "ehirsss": [
        "hissers"
    ], 
    "ehirsssw": [
        "swishers"
    ], 
    "ehirsstw": [
        "swithers"
    ], 
    "ehirssv": [
        "shivers", 
        "shrives"
    ], 
    "ehirssw": [
        "swisher", 
        "wishers"
    ], 
    "ehirst": [
        "theirs", 
        "thiers"
    ], 
    "ehirstt": [
        "tithers", 
        "hitters"
    ], 
    "ehirstu": [
        "hirsute"
    ], 
    "ehirstv": [
        "thrives"
    ], 
    "ehirstw": [
        "writhes", 
        "withers"
    ], 
    "ehirstz": [
        "zithers"
    ], 
    "ehirsv": [
        "shiver", 
        "shrive"
    ], 
    "ehirsvy": [
        "shivery"
    ], 
    "ehirsw": [
        "wisher"
    ], 
    "ehirswzz": [
        "whizzers"
    ], 
    "ehirt": [
        "their"
    ], 
    "ehirtt": [
        "tither", 
        "hitter"
    ], 
    "ehirttw": [
        "whitter"
    ], 
    "ehirtv": [
        "thrive"
    ], 
    "ehirtw": [
        "whiter", 
        "writhe", 
        "wither"
    ], 
    "ehirtz": [
        "zither"
    ], 
    "ehirwzz": [
        "whizzer"
    ], 
    "ehis": [
        "hies"
    ], 
    "ehiss": [
        "ishes", 
        "shies"
    ], 
    "ehisss": [
        "hisses"
    ], 
    "ehisssu": [
        "hussies"
    ], 
    "ehisssw": [
        "swishes"
    ], 
    "ehisst": [
        "heists", 
        "shiest", 
        "thesis"
    ], 
    "ehisstt": [
        "theists"
    ], 
    "ehissu": [
        "usehis"
    ], 
    "ehissw": [
        "wishes"
    ], 
    "ehist": [
        "heist", 
        "isthe", 
        "itshe"
    ], 
    "ehistt": [
        "theist", 
        "tithes"
    ], 
    "ehisttw": [
        "whitest", 
        "wettish"
    ], 
    "ehistw": [
        "whites", 
        "withes"
    ], 
    "ehistwy": [
        "whiteys"
    ], 
    "ehisv": [
        "hives", 
        "shive"
    ], 
    "ehiswzz": [
        "whizzes"
    ], 
    "ehit": [
        "ithe"
    ], 
    "ehitt": [
        "itthe", 
        "tithe"
    ], 
    "ehitv": [
        "ivthe", 
        "vithe"
    ], 
    "ehitvx": [
        "xivthe"
    ], 
    "ehitw": [
        "withe", 
        "white"
    ], 
    "ehitwy": [
        "whitey"
    ], 
    "ehitx": [
        "ixthe", 
        "xithe"
    ], 
    "ehitxx": [
        "xxithe", 
        "xixthe"
    ], 
    "ehiv": [
        "ivhe", 
        "hive"
    ]
}