{
    "ekn": [
        "ken"
    ], 
    "eknnoorrsw": [
        "nonworkers"
    ], 
    "eknnoorrw": [
        "nonworker"
    ], 
    "eknnopsu": [
        "unspoken"
    ], 
    "eknnor": [
        "kronen"
    ], 
    "eknnsu": [
        "sunken"
    ], 
    "eknny": [
        "kenny"
    ], 
    "ekno": [
        "keno"
    ], 
    "eknooprsw": [
        "openworks"
    ], 
    "eknooprw": [
        "openwork"
    ], 
    "eknoopstu": [
        "outspoken"
    ], 
    "eknoors": [
        "snooker", 
        "onkores"
    ], 
    "eknoorss": [
        "snookers"
    ], 
    "eknoorsstw": [
        "stoneworks"
    ], 
    "eknoorstw": [
        "stonework"
    ], 
    "eknops": [
        "spoken"
    ], 
    "eknor": [
        "krone"
    ], 
    "eknorr": [
        "kroner"
    ], 
    "eknorssstu": [
        "sunstrokes"
    ], 
    "eknorsstu": [
        "sunstroke"
    ], 
    "eknorstt": [
        "knotters"
    ], 
    "eknorstw": [
        "networks"
    ], 
    "eknorsuy": [
        "younkers"
    ], 
    "eknorsw": [
        "knowers"
    ], 
    "eknorsy": [
        "yonkers"
    ], 
    "eknortt": [
        "knotter"
    ], 
    "eknortw": [
        "network"
    ], 
    "eknoruy": [
        "younker"
    ], 
    "eknorw": [
        "knower"
    ], 
    "eknory": [
        "yonker"
    ], 
    "eknos": [
        "kenos"
    ], 
    "eknost": [
        "tokens"
    ], 
    "eknostw": [
        "knowest"
    ], 
    "eknosuy": [
        "unyokes"
    ], 
    "eknot": [
        "token"
    ], 
    "eknouy": [
        "unyoke"
    ], 
    "eknow": [
        "woken"
    ], 
    "eknpru": [
        "punker"
    ], 
    "eknpstu": [
        "punkest"
    ], 
    "eknptu": [
        "unkept"
    ], 
    "eknpuy": [
        "punkey"
    ], 
    "eknr": [
        "kern"
    ], 
    "eknrs": [
        "kerns"
    ], 
    "eknrstuy": [
        "turnkeys"
    ], 
    "eknrtuy": [
        "turnkey"
    ], 
    "ekns": [
        "kens"
    ], 
    "eknsu": [
        "nukes"
    ], 
    "eknsy": [
        "ensky"
    ], 
    "eknt": [
        "kent"
    ], 
    "eknu": [
        "nuke"
    ], 
    "eknw": [
        "knew"
    ]
}