{
    "ffii": [
        "ifif"
    ], 
    "ffiilnsy": [
        "sniffily"
    ], 
    "ffiilpsy": [
        "spiffily"
    ], 
    "ffiinosux": [
        "suffixion"
    ], 
    "ffiinst": [
        "tiffins"
    ], 
    "ffiint": [
        "tiffin"
    ], 
    "ffiistxy": [
        "fiftysix"
    ], 
    "ffij": [
        "jiff"
    ], 
    "ffijs": [
        "jiffs"
    ], 
    "ffijy": [
        "jiffy"
    ], 
    "ffiklorst": [
        "forklifts"
    ], 
    "ffiklort": [
        "forklift"
    ], 
    "ffiks": [
        "skiff"
    ], 
    "ffikss": [
        "skiffs"
    ], 
    "ffilllsu": [
        "fulfills"
    ], 
    "ffilllu": [
        "fulfill", 
        "fullfil"
    ], 
    "ffillrtuuy": [
        "fruitfully"
    ], 
    "ffillsu": [
        "fulfils"
    ], 
    "ffilltuy": [
        "fitfully"
    ], 
    "ffillu": [
        "fulfil"
    ], 
    "ffilnrtuuu": [
        "unfruitful"
    ], 
    "ffilnsuy": [
        "snuffily"
    ], 
    "ffilpuy": [
        "puffily"
    ], 
    "ffilrtuu": [
        "fruitful"
    ], 
    "ffilsstu": [
        "fistfuls"
    ], 
    "ffilstu": [
        "fistful"
    ], 
    "ffilstuy": [
        "stuffily"
    ], 
    "ffilsty": [
        "stiffly"
    ], 
    "ffiltu": [
        "fitful"
    ], 
    "ffim": [
        "miff"
    ], 
    "ffimnsu": [
        "muffins"
    ], 
    "ffimnu": [
        "muffin"
    ], 
    "ffimorsu": [
        "fusiform"
    ], 
    "ffims": [
        "miffs"
    ], 
    "ffimy": [
        "miffy"
    ], 
    "ffinoost": [
        "finfoots"
    ], 
    "ffinoprst": [
        "offprints"
    ], 
    "ffinoprt": [
        "offprint"
    ], 
    "ffinops": [
        "spinoff"
    ], 
    "ffinopss": [
        "spinoffs"
    ], 
    "ffinopst": [
        "pontiffs"
    ], 
    "ffinopt": [
        "pontiff"
    ], 
    "ffinosssuu": [
        "suffusions"
    ], 
    "ffinossuu": [
        "suffusion"
    ], 
    "ffinpsu": [
        "puffins"
    ], 
    "ffinpu": [
        "puffin"
    ], 
    "ffins": [
        "sniff"
    ], 
    "ffinss": [
        "sniffs"
    ], 
    "ffinsy": [
        "sniffy"
    ], 
    "ffio": [
        "offi"
    ], 
    "ffiopr": [
        "ripoff"
    ], 
    "ffioprs": [
        "ripoffs"
    ], 
    "ffiopst": [
        "tipoffs"
    ], 
    "ffiopt": [
        "tipoff"
    ], 
    "ffiortu": [
        "fruitof"
    ], 
    "ffiorty": [
        "fortify"
    ], 
    "ffiorx": [
        "fixfor"
    ], 
    "ffiosst": [
        "soffits"
    ], 
    "ffiost": [
        "soffit"
    ], 
    "ffiottwy": [
        "fiftytwo"
    ], 
    "ffips": [
        "spiff"
    ], 
    "ffipsy": [
        "spiffy"
    ], 
    "ffir": [
        "riff"
    ], 
    "ffirs": [
        "riffs"
    ], 
    "ffisst": [
        "stiffs"
    ], 
    "ffist": [
        "tiffs", 
        "stiff"
    ], 
    "ffisux": [
        "suffix"
    ], 
    "ffit": [
        "tiff", 
        "fift"
    ], 
    "ffity": [
        "fifty"
    ], 
    "ffiy": [
        "iffy"
    ]
}