{
    "glo": [
        "log"
    ], 
    "gloo": [
        "logo"
    ], 
    "gloooooprtyz": [
        "protozoology"
    ], 
    "glooopsy": [
        "posology"
    ], 
    "glooopty": [
        "topology"
    ], 
    "gloooty": [
        "otology"
    ], 
    "gloooy": [
        "oology"
    ], 
    "gloooyz": [
        "zoology"
    ], 
    "gloopr": [
        "prolog"
    ], 
    "glooprs": [
        "prologs"
    ], 
    "glooptyy": [
        "typology"
    ], 
    "glooruy": [
        "urology"
    ], 
    "gloos": [
        "logos"
    ], 
    "glooy": [
        "ology"
    ], 
    "glop": [
        "glop"
    ], 
    "glops": [
        "glops"
    ], 
    "glorssy": [
        "grossly"
    ], 
    "glorsw": [
        "growls"
    ], 
    "glorw": [
        "growl"
    ], 
    "glorwy": [
        "growly"
    ], 
    "glory": [
        "glory"
    ], 
    "glos": [
        "slog", 
        "logs"
    ], 
    "gloss": [
        "slogs", 
        "gloss"
    ], 
    "glossy": [
        "glossy"
    ], 
    "glosw": [
        "glows"
    ], 
    "glouv": [
        "vulgo"
    ], 
    "glow": [
        "glow"
    ], 
    "gloy": [
        "logy"
    ]
}