{
    "ijll": [
        "jill"
    ], 
    "ijllloy": [
        "jollily"
    ], 
    "ijlloty": [
        "jollity", 
        "joltily"
    ], 
    "ijlls": [
        "jills"
    ], 
    "ijllssttu": [
        "stilljust"
    ], 
    "ijlmpuy": [
        "jumpily"
    ], 
    "ijlnoqsu": [
        "jonquils"
    ], 
    "ijlnoqu": [
        "jonquil"
    ], 
    "ijlnoty": [
        "jointly"
    ], 
    "ijlst": [
        "jilts"
    ], 
    "ijlsuu": [
        "julius"
    ], 
    "ijlt": [
        "jilt"
    ]
}